{"type":"Topology","objects":{"building_neighborhood_capacity_program.geo":{"type":"GeometryCollection","geometries":[{"type":"Polygon","properties":{"LocationDisplay":"Flint, Michigan","NumberOfProjects":1,"id":22566080},"arcs":[[0]]},{"type":"Polygon","properties":{"LocationDisplay":"Memphis, Tennessee","NumberOfProjects":1,"id":22566081},"arcs":[[1],[2],[3],[4]]},{"type":"Polygon","properties":{"LocationDisplay":"Milwaukee, Wisconsin","NumberOfProjects":1,"id":22566082},"arcs":[[5]]}]}},"arcs":[[[9957,9865],[0,1],[1,0],[0,1],[0,-1],[0,1],[1,0],[1,0],[1,0],[1,0],[1,0],[0,1],[1,0],[0,1],[0,1],[1,0],[0,-1],[0,-1],[2,0],[1,0],[1,0],[1,0],[0,2],[0,1],[0,1],[0,1],[0,1],[0,1],[-1,0],[0,1],[0,2],[0,1],[1,0],[1,2],[0,1],[0,1],[2,4],[-1,-1],[0,1],[-1,-1],[0,1],[-1,-2],[0,1],[-1,-2],[1,0],[-1,0],[0,-1],[-1,0],[0,1],[0,1],[0,1],[0,1],[0,2],[0,2],[0,1],[0,1],[0,1],[0,1],[-1,0],[-1,0],[0,1],[0,1],[0,1],[0,1],[0,1],[0,1],[0,1],[0,1],[1,1],[-1,0],[-1,0],[1,3],[0,1],[0,1],[0,1],[0,1],[0,1],[0,1],[0,1],[0,1],[1,4],[0,3],[0,1],[1,0],[0,1],[0,1],[0,1],[0,1],[1,1],[0,1],[0,1],[0,1],[-1,0],[0,1],[-1,0],[0,1],[-1,1],[-1,1],[1,1],[0,2],[0,1],[0,1],[0,1],[0,1],[0,1],[-1,-1],[0,1],[1,2],[0,1],[0,1],[1,1],[0,-1],[0,-1],[1,1],[0,1],[0,5],[0,5],[0,3],[0,2],[0,3],[0,1],[0,4],[-1,1],[0,4],[1,0],[0,1],[0,1],[0,1],[0,1],[0,2],[0,2],[0,2],[0,5],[0,3],[1,0],[1,0],[0,1],[0,4],[2,0],[0,-5],[1,0],[1,0],[1,0],[1,0],[1,0],[1,0],[1,0],[1,1],[1,0],[1,0],[1,0],[1,0],[2,0],[1,0],[1,0],[1,0],[1,0],[1,0],[1,0],[-1,-4],[0,-2],[0,-1],[0,-1],[0,-1],[0,-2],[0,-3],[0,-4],[0,-2],[0,-2],[0,-1],[0,-1],[0,1],[1,0],[0,1],[1,0],[0,1],[1,0],[0,1],[1,0],[0,1],[1,0],[0,1],[0,5],[1,0],[0,-3],[0,-1],[1,0],[0,-7],[1,0],[0,-1],[0,1],[0,-1],[0,-1],[0,-4],[0,-1],[-1,0],[-1,0],[0,3],[0,2],[0,-1],[-1,0],[0,1],[0,6],[-1,0],[0,-2],[-1,0],[0,-1],[1,1],[0,-1],[-1,0],[0,-1],[-1,1],[0,-1],[0,-1],[0,1],[0,-1],[-1,0],[0,-1],[-1,0],[0,-1],[0,-2],[0,-2],[1,0],[1,0],[2,0],[0,-4],[0,-4],[0,-2],[0,-2],[0,-2],[0,-1],[0,-1],[0,-1],[0,-2],[0,-3],[0,-1],[0,-1],[0,-1],[0,-1],[0,-2],[0,-2],[0,-1],[0,-2],[0,-1],[0,-1],[0,-1],[0,-1],[0,-1],[0,-1],[0,-1],[0,-3],[0,-1],[0,-1],[0,-1],[0,-1],[0,-1],[0,-1],[0,-2],[0,-2],[0,-2],[0,-2],[0,-1],[-1,0],[-1,0],[0,-2],[0,-4],[0,-3],[0,-1],[0,-6],[0,-2],[-1,0],[-1,0],[-1,0],[0,-1],[0,-8],[-1,0],[-1,-1],[-1,0],[-1,0],[-2,0],[-1,0],[-1,0],[-1,0],[-1,0],[0,-6],[-1,0],[0,1],[0,-1],[0,-1],[0,-1],[0,-1],[0,-1],[0,-1],[0,-1],[0,-1],[0,-1],[0,-1],[0,-1],[0,-1],[0,-1],[0,-4],[0,-3],[0,-2],[-1,0],[-2,0],[-1,0],[-1,-1],[-2,0],[-1,0],[-1,0],[-1,0],[-1,0],[-1,0],[-1,0],[0,-5],[2,0],[0,-4],[-1,-1],[-1,0],[0,-2],[0,-1],[0,-1],[0,-1],[0,-1],[-2,0],[0,3],[1,3],[0,1],[-1,0],[-1,-1],[0,1],[0,1],[0,2],[0,1],[0,2],[0,3],[-1,0],[-1,0],[0,-1],[0,3],[-1,0],[0,-3],[-1,0],[0,1],[0,-1],[-1,0],[0,4],[0,1],[-1,0],[0,1],[1,0],[0,1],[0,1],[1,0],[1,0],[0,1],[-2,0],[-1,0],[0,2],[0,3],[0,1],[0,1]],[[8146,7],[0,3],[1,1],[0,2],[0,3],[1,1],[0,1],[1,1],[1,1],[3,4],[0,1],[0,1],[1,0],[0,2],[0,1],[1,2],[1,1],[0,1],[1,0],[0,1],[2,0],[0,1],[2,0],[0,1],[1,0],[1,0],[1,0],[1,-1],[1,0],[1,0],[1,0],[1,0],[1,1],[1,1],[1,0],[1,1],[1,1],[0,1],[-1,0],[1,1],[1,5],[1,1],[0,1],[0,1],[1,2],[0,2],[0,1],[0,8],[0,5],[0,6],[0,9],[4,36],[0,2],[1,7],[0,1],[0,18],[1,2],[0,3],[0,2],[1,1],[0,1],[0,1],[0,1],[1,2],[0,1],[1,2],[1,5],[1,2],[2,2],[0,1],[1,2],[1,0],[1,-1],[1,-3],[1,-1],[0,-1],[6,-14],[2,-2],[1,0],[1,0],[1,1],[1,2],[1,1],[0,1],[0,1],[2,5],[0,2],[1,1],[0,1],[0,1],[0,1],[1,1],[0,1],[1,3],[0,1],[0,1],[0,1],[0,1],[1,1],[0,2],[0,1],[0,1],[-1,5],[0,5],[0,1],[0,1],[0,1],[-1,1],[0,4],[0,5],[0,5],[0,2],[-1,3],[0,2],[0,6],[0,1],[0,10],[0,13],[0,1],[0,1],[0,7],[0,2],[2,4],[0,1],[0,1],[1,2],[0,1],[0,1],[1,1],[0,1],[0,1],[0,1],[1,0],[0,-1],[1,0],[1,0],[1,0],[0,1],[0,1],[0,1],[0,1],[0,1],[1,-1],[0,1],[0,1],[0,1],[0,2],[0,2],[0,1],[0,2],[0,1],[1,0],[1,1],[1,0],[1,0],[1,-1],[0,1],[1,1],[0,2],[0,2],[1,2],[0,1],[0,1],[0,1],[0,1],[1,0],[0,1],[-1,0],[0,1],[0,1],[0,3],[0,1],[0,9],[-1,0],[0,1],[0,2],[-1,4],[0,1],[0,1],[0,1],[0,1],[0,1],[1,0],[1,0],[0,1],[1,0],[0,-1],[0,-1],[0,-1],[0,-1],[0,-1],[0,-1],[0,-1],[0,-3],[0,-1],[0,-1],[0,-1],[0,-5],[0,-1],[0,-1],[0,-1],[0,-2],[0,-1],[0,-1],[0,1],[1,0],[0,1],[0,1],[0,1],[0,1],[1,3],[0,1],[0,1],[0,1],[1,5],[1,3],[0,2],[1,4],[1,0],[1,0],[0,1],[0,1],[1,0],[0,1],[1,0],[1,0],[0,-1],[0,-1],[0,-1],[0,-1],[0,-1],[0,-1],[0,-1],[0,-1],[0,-1],[1,0],[0,-1],[1,0],[0,1],[0,1],[0,1],[1,0],[0,1],[0,1],[0,1],[1,0],[1,0],[0,1],[1,0],[1,1],[1,0],[0,1],[1,0],[1,0],[0,1],[1,0],[0,1],[1,0],[1,0],[0,1],[1,0],[0,1],[0,-1],[0,-1],[0,1],[0,-1],[0,1],[1,0],[0,-1],[0,-1],[0,-1],[-1,0],[0,1],[0,-1],[0,-1],[1,0],[0,-1],[-1,-2],[1,0],[0,-2],[0,-6],[0,-2],[0,-1],[0,-1],[0,-1],[0,-1],[0,-1],[0,-1],[0,-1],[0,-1],[1,0],[1,0],[1,0],[0,-1],[0,-1],[0,-1],[0,-1],[0,-2],[0,-2],[1,0],[0,-1],[1,-1],[0,-1],[0,-1],[0,-1],[0,-1],[1,0],[0,-1],[0,-1],[0,1],[1,1],[0,1],[0,1],[0,1],[0,1],[0,1],[0,1],[0,1],[0,1],[0,3],[0,2],[1,0],[1,0],[1,0],[1,0],[0,-1],[1,0],[0,-1],[-1,0],[0,-1],[0,-1],[0,-1],[0,-1],[-1,-1],[0,-1],[0,-1],[1,0],[-1,-4],[0,-1],[0,-1],[0,-1],[0,-4],[1,0],[0,-1],[0,-2],[0,-1],[0,-1],[0,-1],[0,-1],[0,-1],[0,-1],[0,-1],[0,-1],[0,-1],[0,-1],[0,-1],[1,-1],[0,-1],[0,-1],[0,-1],[-1,0],[-1,0],[0,-1],[0,-1],[0,-1],[0,-3],[0,-1],[1,-1],[1,0],[0,-1],[0,-3],[0,-1],[0,-1],[0,-1],[0,-1],[0,-1],[0,-1],[0,-2],[0,-1],[0,-1],[0,-1],[0,-1],[0,-1],[0,-1],[0,-2],[0,-1],[1,0],[1,0],[1,-1],[1,0],[2,0],[1,0],[0,1],[1,1],[0,1],[0,1],[0,1],[1,0],[0,1],[0,1],[0,-1],[0,1],[0,1],[1,2],[0,2],[1,1],[0,1],[0,2],[0,1],[1,1],[0,1],[1,2],[0,1],[1,0],[0,-1],[1,0],[1,-1],[0,1],[1,0],[1,0],[1,0],[1,0],[1,0],[1,0],[1,0],[1,0],[1,0],[1,0],[1,0],[1,0],[1,0],[1,0],[1,0],[1,0],[1,0],[1,0],[1,0],[1,0],[1,0],[1,0],[0,1],[1,0],[1,0],[1,1],[1,0],[1,0],[1,-1],[1,0],[1,0],[1,1],[1,0],[1,0],[0,1],[1,0],[0,-1],[0,1],[1,0],[1,1],[1,1],[0,1],[1,1],[1,1],[1,0],[0,1],[1,-1],[1,0],[1,0],[1,0],[0,-1],[1,0],[1,0],[1,0],[1,0],[1,0],[1,0],[1,0],[0,-1],[0,-1],[0,-3],[0,-1],[0,-2],[0,-5],[0,-2],[0,1],[0,1],[-1,0],[0,1],[0,1],[-1,1],[0,1],[-1,0],[0,-1],[0,1],[-1,0],[0,-1],[0,-1],[-1,-1],[-1,0],[0,-1],[0,-1],[0,-1],[0,1],[-1,0],[-1,1],[0,-1],[0,1],[0,1],[-1,0],[-1,0],[-1,0],[0,1],[-1,-1],[-1,0],[0,-1],[-1,0],[0,-1],[-1,0],[-1,-1],[0,-1],[-1,0],[0,-1],[-1,-1],[-1,0],[0,-1],[-1,0],[0,-1],[-1,-1],[0,-1],[-1,-1],[0,-1],[-1,0],[0,-1],[0,-1],[0,-1],[0,-1],[0,-1],[0,-1],[-1,0],[0,-1],[0,-1],[0,-1],[0,1],[-1,2],[0,1],[0,1],[-1,-1],[0,1],[0,-1],[-1,-1],[0,1],[0,1],[-1,1],[0,1],[0,1],[0,1],[0,1],[0,1],[0,1],[0,1],[0,1],[0,1],[0,1],[-1,0],[-2,0],[-1,0],[0,1],[0,1],[-1,1],[1,-3],[-1,0],[0,-1],[0,-1],[0,-1],[0,-1],[0,-1],[0,-1],[-1,-1],[0,-1],[-1,0],[0,-1],[1,0],[0,-1],[0,-1],[0,-1],[0,-1],[0,-1],[1,0],[0,-1],[0,-1],[0,-1],[0,-1],[0,-1],[0,-1],[0,-1],[0,-1],[0,-1],[0,-1],[0,-1],[1,0],[0,-1],[1,0],[0,-3],[-1,0],[-1,0],[-1,0],[0,1],[0,1],[0,-1],[0,-1],[-1,0],[0,1],[0,-1],[-1,0],[0,-1],[0,-1],[0,-1],[0,-1],[1,-1],[0,-1],[0,-1],[0,-1],[0,-1],[0,-1],[0,-1],[0,-1],[0,-1],[-1,-1],[0,-1],[0,-1],[-1,-1],[0,-1],[0,-1],[0,-1],[0,1],[1,0],[0,1],[1,1],[0,1],[1,0],[0,-1],[0,-1],[0,-2],[0,-1],[0,-2],[0,-1],[0,-1],[0,-1],[1,1],[0,1],[1,-3],[0,-1],[1,0],[0,1],[1,1],[0,-3],[0,-1],[0,-1],[0,-3],[-1,0],[0,-1],[0,-1],[0,-1],[-1,-6],[0,-4],[1,0],[0,-1],[0,-1],[0,-1],[0,-2],[1,-1],[0,-1],[0,-1],[0,-1],[0,-1],[-1,0],[0,1],[0,-1],[0,-1],[-1,0],[0,2],[-1,0],[0,3],[0,-1],[-1,-1],[0,-2],[1,0],[0,-1],[1,-4],[-1,1],[-1,0],[0,1],[0,1],[0,1],[0,1],[0,1],[0,1],[-1,0],[-1,-1],[0,-1],[-1,0],[0,1],[0,-1],[0,-1],[0,-1],[0,-1],[0,-1],[0,-1],[0,-1],[-1,0],[0,1],[0,2],[-1,0],[0,-1],[0,-2],[0,-1],[0,-3],[0,-2],[0,-1],[0,-1],[0,-1],[0,-2],[0,-1],[0,-3],[0,-1],[0,-1],[0,-1],[0,-1],[-1,1],[0,1],[-1,0],[0,1],[0,1],[-1,0],[0,1],[0,1],[-1,0],[0,1],[0,1],[0,1],[-1,0],[0,1],[0,1],[0,1],[-1,0],[0,1],[-1,0],[0,-1],[-1,0],[-1,0],[0,1],[0,-1],[0,1],[-1,0],[0,1],[-1,0],[-1,0],[0,1],[-1,0],[0,1],[-1,0],[0,1],[-1,0],[0,1],[-1,0],[0,-3],[0,-1],[0,-1],[0,-1],[0,-5],[0,-1],[0,-3],[0,-1],[0,-1],[0,-1],[0,-1],[0,-1],[0,-1],[0,-1],[0,-1],[0,-1],[0,-1],[0,-2],[0,-1],[0,-1],[-1,0],[0,1],[-1,0],[0,1],[-1,0],[0,-1],[0,-1],[0,-1],[1,0],[0,-1],[1,0],[1,0],[1,-1],[0,-1],[1,0],[0,-1],[0,-3],[0,-1],[0,-1],[0,-1],[0,-1],[-1,0],[0,-2],[0,-2],[0,-1],[0,-1],[1,0],[0,-1],[0,-2],[0,-1],[0,-1],[0,-1],[0,-1],[0,-1],[0,-4],[0,-1],[0,-1],[0,-3],[0,-1],[0,-1],[0,-1],[0,-1],[1,1],[0,-1],[0,1],[1,-1],[0,1],[0,1],[1,0],[1,0],[0,-1],[0,-1],[1,0],[1,0],[1,0],[0,-1],[0,-1],[1,0],[1,-1],[1,0],[2,0],[0,-1],[0,-2],[0,-1],[-1,0],[0,-1],[1,0],[0,-1],[0,1],[1,0],[0,-3],[0,-1],[0,-1],[-1,-1],[0,1],[-1,0],[0,1],[0,-1],[-1,0],[0,-2],[0,-1],[1,0],[0,-1],[0,-2],[0,-1],[1,0],[0,1],[-1,0],[1,0],[0,1],[2,0],[0,-1],[0,1],[0,-1],[1,0],[1,0],[0,-3],[0,-1],[0,-1],[0,-1],[0,-1],[0,-1],[1,0],[0,-1],[0,-1],[0,-1],[0,-3],[0,-1],[-1,-2],[0,-1],[0,-1],[0,1],[0,3],[-1,2],[-1,0],[0,-6],[-2,3],[0,3],[0,2],[0,1],[0,1],[0,1],[0,1],[0,1],[0,1],[1,0],[0,2],[-1,0],[0,-1],[-1,0],[0,1],[-1,0],[0,-5],[0,-1],[0,-5],[2,-5],[0,1],[-1,0],[0,1],[0,1],[-1,0],[0,1],[-1,0],[0,1],[0,1],[0,1],[0,1],[0,2],[0,1],[0,1],[-1,0],[0,2],[1,0],[0,1],[-1,0],[-1,0],[0,1],[-1,0],[0,1],[-1,0],[0,-1],[0,-2],[0,-1],[0,1],[-1,1],[0,1],[0,1],[0,1],[-1,0],[0,-1],[0,-1],[0,-1],[1,0],[0,-1],[0,-1],[0,-1],[0,-2],[0,-1],[0,-2],[0,-1],[0,-1],[0,-1],[0,-1],[0,-1],[0,-1],[0,-2],[-1,0],[-1,0],[0,-1],[0,-1],[0,-1],[0,-1],[0,-1],[0,-1],[0,-1],[0,-1],[0,-1],[0,1],[-1,0],[0,-1],[0,-1],[0,-1],[0,-1],[0,-4],[0,-2],[-1,0],[0,-1],[0,-1],[0,-1],[0,-1],[0,-1],[-1,0],[0,-1],[0,-1],[0,-1],[0,-1],[0,1],[-1,-1],[0,1],[-1,0],[0,-1],[-1,0],[-1,0],[-1,0],[0,-1],[0,-1],[0,-1],[0,-2],[0,-2],[0,-2],[0,-2],[-1,0],[0,-1],[0,-1],[0,-1],[0,-1],[0,-3],[1,0],[0,-1],[0,-1],[1,-2],[0,-1],[-1,0],[-1,0],[-1,0],[-1,0],[-1,0],[-1,0],[-1,0],[-1,0],[-1,0],[-1,0],[0,1],[-1,0],[-2,1],[0,-2],[-1,0],[0,1],[-1,0],[-1,0],[-1,0],[-1,0],[-1,0],[-1,0],[-1,0],[-1,0],[-1,0],[-1,0],[-1,0],[-2,0],[-1,0],[-1,0],[-1,0],[-1,0],[-1,0],[-1,0],[-1,0],[-1,0],[-1,0],[-1,0],[-1,0],[-1,0],[-1,0],[-2,0],[-1,0],[-1,0],[-1,0],[-1,0],[-1,0],[-1,0],[-1,0],[-1,0],[-1,0],[-1,0],[-1,0],[-1,0],[-1,0],[-2,0],[-1,0],[-1,0],[-1,0],[-3,0],[-1,0],[-1,0],[-1,0],[-1,0],[-1,0],[-1,0],[-1,0],[-1,0],[-1,0],[-1,0],[-2,0],[-1,0],[-1,0],[-1,0],[-1,0],[-1,0],[-1,0],[-1,0],[-1,0],[-1,0],[-3,0],[-2,0],[-5,0],[-3,0],[-1,0],[-3,0],[-1,0],[-1,0],[-1,0],[0,1],[-1,0],[-1,0],[-1,0],[-1,0],[-2,0],[-1,0],[-1,0],[-1,0],[-3,0],[-1,0],[-1,0],[-4,0],[-1,0],[-1,0],[-1,0],[-1,0],[-1,0],[-1,0],[0,3],[0,1],[0,1]],[[8277,199],[0,-1],[0,-1],[0,-1],[0,-1],[0,-1],[1,0],[0,-1],[1,0],[1,-1],[1,-1],[0,-1],[1,0],[1,0],[0,1],[0,1],[0,1],[0,1],[1,-1],[0,2],[0,1],[0,1],[0,1],[1,0],[-1,-1],[0,-1],[0,-2],[0,-1],[1,0],[0,1],[0,5],[0,1],[1,0],[0,-1],[0,1],[0,2],[0,1],[0,1],[-1,0],[0,1],[0,1],[0,1],[-1,0],[0,1],[0,1],[0,1],[0,1],[0,1],[0,1],[0,2],[0,1],[-1,3],[0,1],[0,1],[0,1],[0,1],[0,2],[0,2],[0,1],[0,1],[0,2],[0,1],[0,1],[0,1],[0,1],[0,1],[0,1],[0,-1],[-1,-1],[0,-1],[0,-1],[-1,-1],[-1,-2],[-1,-1],[0,-1],[-1,-1],[0,-1],[0,-1],[-1,0],[0,-1],[0,-1],[0,-1],[0,-1],[0,-1],[0,-1],[0,-1],[0,-3],[0,-1],[0,-1],[0,-1],[0,-3],[0,-1],[0,-1],[0,-1],[0,-1],[0,-1],[0,-1],[0,-1],[0,-1],[0,-1],[0,-1]],[[8288,157],[0,-1],[0,1],[1,-2],[0,-2],[1,4],[0,-1],[0,1],[0,1],[1,1],[0,1],[-1,0],[0,1],[0,1],[0,1],[0,-1],[-1,-1],[0,-1],[0,-1],[-1,0],[0,-1],[0,-1]],[[8287,158],[0,-1],[1,0],[0,1],[0,1],[0,-1],[-1,0]],[[8790,9915],[0,1],[0,1],[0,1],[0,1],[0,2],[0,1],[0,1],[0,1],[1,0],[1,1],[1,0],[0,1],[1,0],[0,1],[0,1],[0,2],[0,1],[1,0],[1,0],[0,-1],[0,-1],[0,-1],[0,-1],[0,-1],[0,-1],[0,-1],[0,-1],[0,-1],[-1,0],[0,-1],[0,-1],[0,-1],[0,-1],[0,-1],[1,0],[0,-1],[-1,0],[0,-1],[0,-1],[0,-1],[1,1],[0,-1],[0,-3],[0,-1],[0,-1],[0,-1],[0,-1],[0,-1],[-1,0],[0,-1],[-1,0],[0,-2],[0,1],[-1,0],[0,1],[-1,0],[0,1],[0,1],[0,1],[0,3],[0,1],[0,2],[0,1],[-1,0],[0,-1],[0,1],[0,2],[-1,-1]]],"transform":{"scale":[0.0036092310331033114,0.0008085956295629562],"translate":[-119.7093499,34.994188]}}