{"type":"Topology","objects":{"promise_zones.geo":{"type":"GeometryCollection","geometries":[{"type":"Polygon","properties":{"InitiativeTitle":"Promise Zones","LocationDisplay":"Allendale, SC","NumberOfProjects":1,"id":22271024},"popupTemplate":"<strong>{InitiativeTitle}</strong><BR>{LocationDisplay}","arcs":[[0,1,2,3]]},{"type":"Polygon","properties":{"InitiativeTitle":"Promise Zones","LocationDisplay":"Allendale, SC","NumberOfProjects":1,"id":22271024},"popupTemplate":"<strong>{InitiativeTitle}</strong><BR>{LocationDisplay}","arcs":[[0,1,2,3]]},{"type":"Polygon","properties":{"InitiativeTitle":"Promise Zones","LocationDisplay":"Atoka, OK","NumberOfProjects":1,"id":22658158},"popupTemplate":"<strong>{InitiativeTitle}</strong><BR>{LocationDisplay}","arcs":[[4,5,6,7,8],[9]]},{"type":"Polygon","properties":{"InitiativeTitle":"Promise Zones","LocationDisplay":"Atoka, OK","NumberOfProjects":1,"id":22658158},"popupTemplate":"<strong>{InitiativeTitle}</strong><BR>{LocationDisplay}","arcs":[[4,5,6,7,8],[9]]},{"type":"Polygon","properties":{"InitiativeTitle":"Promise Zones","LocationDisplay":"Bamberg, SC","NumberOfProjects":1,"id":22657649},"popupTemplate":"<strong>{InitiativeTitle}</strong><BR>{LocationDisplay}","arcs":[[10,11,-2,12]]},{"type":"Polygon","properties":{"InitiativeTitle":"Promise Zones","LocationDisplay":"Bamberg, SC","NumberOfProjects":1,"id":22657649},"popupTemplate":"<strong>{InitiativeTitle}</strong><BR>{LocationDisplay}","arcs":[[10,11,-2,12]]},{"type":"Polygon","properties":{"InitiativeTitle":"Promise Zones","LocationDisplay":"Barnwell, SC","NumberOfProjects":1,"id":22657657},"popupTemplate":"<strong>{InitiativeTitle}</strong><BR>{LocationDisplay}","arcs":[[-13,-1,13]]},{"type":"Polygon","properties":{"InitiativeTitle":"Promise Zones","LocationDisplay":"Barnwell, SC","NumberOfProjects":1,"id":22657657},"popupTemplate":"<strong>{InitiativeTitle}</strong><BR>{LocationDisplay}","arcs":[[-13,-1,13]]},{"type":"Polygon","properties":{"InitiativeTitle":"Promise Zones","LocationDisplay":"Bell, KY","NumberOfProjects":1,"id":22658197},"popupTemplate":"<strong>{InitiativeTitle}</strong><BR>{LocationDisplay}","arcs":[[14,15,16,17,18,19]]},{"type":"Polygon","properties":{"InitiativeTitle":"Promise Zones","LocationDisplay":"Bell, KY","NumberOfProjects":1,"id":22658197},"popupTemplate":"<strong>{InitiativeTitle}</strong><BR>{LocationDisplay}","arcs":[[14,15,16,17,18,19]]},{"type":"Polygon","properties":{"InitiativeTitle":"Promise Zones","LocationDisplay":"Bennett, SD","NumberOfProjects":1,"id":22658507},"popupTemplate":"<strong>{InitiativeTitle}</strong><BR>{LocationDisplay}","arcs":[[20,21,22]]},{"type":"Polygon","properties":{"InitiativeTitle":"Promise Zones","LocationDisplay":"Bennett, SD","NumberOfProjects":1,"id":22658507},"popupTemplate":"<strong>{InitiativeTitle}</strong><BR>{LocationDisplay}","arcs":[[20,21,22]]},{"type":"Polygon","properties":{"InitiativeTitle":"Promise Zones","LocationDisplay":"Bryan, OK","NumberOfProjects":1,"id":22658159},"popupTemplate":"<strong>{InitiativeTitle}</strong><BR>{LocationDisplay}","arcs":[[-9,23,24]]},{"type":"Polygon","properties":{"InitiativeTitle":"Promise Zones","LocationDisplay":"Bryan, OK","NumberOfProjects":1,"id":22658159},"popupTemplate":"<strong>{InitiativeTitle}</strong><BR>{LocationDisplay}","arcs":[[-9,23,24]]},{"type":"Polygon","properties":{"InitiativeTitle":"Promise Zones","LocationDisplay":"Camden, NJ","NumberOfProjects":1,"id":22271015},"popupTemplate":"<strong>{InitiativeTitle}</strong><BR>{LocationDisplay}","arcs":[[25,26,27,28,29,30,31]]},{"type":"Polygon","properties":{"InitiativeTitle":"Promise Zones","LocationDisplay":"Choctaw Nation of Oklahoma","NumberOfProjects":1,"id":851},"popupTemplate":"<strong>{InitiativeTitle}</strong><BR>{LocationDisplay}","arcs":[[32]]},{"type":"Polygon","properties":{"InitiativeTitle":"Promise Zones","LocationDisplay":"Choctaw, OK","NumberOfProjects":1,"id":22658185},"popupTemplate":"<strong>{InitiativeTitle}</strong><BR>{LocationDisplay}","arcs":[[-8,33,-24]]},{"type":"Polygon","properties":{"InitiativeTitle":"Promise Zones","LocationDisplay":"Choctaw, OK","NumberOfProjects":1,"id":22658185},"popupTemplate":"<strong>{InitiativeTitle}</strong><BR>{LocationDisplay}","arcs":[[-8,33,-24]]},{"type":"Polygon","properties":{"InitiativeTitle":"Promise Zones","LocationDisplay":"City of Los Angeles","NumberOfProjects":1,"id":849},"popupTemplate":"<strong>{InitiativeTitle}</strong><BR>{LocationDisplay}","arcs":[[34]]},{"type":"Polygon","properties":{"InitiativeTitle":"Promise Zones","LocationDisplay":"City of Minneapolis","NumberOfProjects":1,"id":839},"popupTemplate":"<strong>{InitiativeTitle}</strong><BR>{LocationDisplay}","arcs":[[35]]},{"type":"Polygon","properties":{"InitiativeTitle":"Promise Zones","LocationDisplay":"City of San Antonio","NumberOfProjects":1,"id":847},"popupTemplate":"<strong>{InitiativeTitle}</strong><BR>{LocationDisplay}","arcs":[[36]]},{"type":"Polygon","properties":{"InitiativeTitle":"Promise Zones","LocationDisplay":"Clay, KY","NumberOfProjects":1,"id":22658198},"popupTemplate":"<strong>{InitiativeTitle}</strong><BR>{LocationDisplay}","arcs":[[37,-16,38,39]]},{"type":"Polygon","properties":{"InitiativeTitle":"Promise Zones","LocationDisplay":"Clay, KY","NumberOfProjects":1,"id":22658198},"popupTemplate":"<strong>{InitiativeTitle}</strong><BR>{LocationDisplay}","arcs":[[37,-16,38,39]]},{"type":"Polygon","properties":{"InitiativeTitle":"Promise Zones","LocationDisplay":"Coal, OK","NumberOfProjects":1,"id":22658184},"popupTemplate":"<strong>{InitiativeTitle}</strong><BR>{LocationDisplay}","arcs":[[-6,40]]},{"type":"Polygon","properties":{"InitiativeTitle":"Promise Zones","LocationDisplay":"Coal, OK","NumberOfProjects":1,"id":22658184},"popupTemplate":"<strong>{InitiativeTitle}</strong><BR>{LocationDisplay}","arcs":[[-6,40]]},{"type":"Polygon","properties":{"InitiativeTitle":"Promise Zones","LocationDisplay":"Colleton, SC","NumberOfProjects":1,"id":22657658},"popupTemplate":"<strong>{InitiativeTitle}</strong><BR>{LocationDisplay}","arcs":[[-12,41,42]]},{"type":"Polygon","properties":{"InitiativeTitle":"Promise Zones","LocationDisplay":"Colleton, SC","NumberOfProjects":1,"id":22657658},"popupTemplate":"<strong>{InitiativeTitle}</strong><BR>{LocationDisplay}","arcs":[[-12,41,42]]},{"type":"Polygon","properties":{"InitiativeTitle":"Promise Zones","LocationDisplay":"Hampton, SC","NumberOfProjects":1,"id":22657672},"popupTemplate":"<strong>{InitiativeTitle}</strong><BR>{LocationDisplay}","arcs":[[-3,-43,43,44,45]]},{"type":"Polygon","properties":{"InitiativeTitle":"Promise Zones","LocationDisplay":"Hampton, SC","NumberOfProjects":1,"id":22657672},"popupTemplate":"<strong>{InitiativeTitle}</strong><BR>{LocationDisplay}","arcs":[[-3,-43,43,44,45]]},{"type":"Polygon","properties":{"InitiativeTitle":"Promise Zones","LocationDisplay":"Harlan, KY","NumberOfProjects":1,"id":22658199},"popupTemplate":"<strong>{InitiativeTitle}</strong><BR>{LocationDisplay}","arcs":[[46,47,48,49,-18]]},{"type":"Polygon","properties":{"InitiativeTitle":"Promise Zones","LocationDisplay":"Harlan, KY","NumberOfProjects":1,"id":22658199},"popupTemplate":"<strong>{InitiativeTitle}</strong><BR>{LocationDisplay}","arcs":[[46,47,48,49,-18]]},{"type":"Polygon","properties":{"InitiativeTitle":"Promise Zones","LocationDisplay":"Hartford Mayors Office","NumberOfProjects":1,"id":840},"popupTemplate":"<strong>{InitiativeTitle}</strong><BR>{LocationDisplay}","arcs":[[50]]},{"type":"Polygon","properties":{"InitiativeTitle":"Promise Zones","LocationDisplay":"Hartford, CT","NumberOfProjects":1,"id":22271016},"popupTemplate":"<strong>{InitiativeTitle}</strong><BR>{LocationDisplay}","arcs":[[51]]},{"type":"Polygon","properties":{"InitiativeTitle":"Promise Zones","LocationDisplay":"Haskell, OK","NumberOfProjects":1,"id":22658186},"popupTemplate":"<strong>{InitiativeTitle}</strong><BR>{LocationDisplay}","arcs":[[52]]},{"type":"Polygon","properties":{"InitiativeTitle":"Promise Zones","LocationDisplay":"Haskell, OK","NumberOfProjects":1,"id":22658186},"popupTemplate":"<strong>{InitiativeTitle}</strong><BR>{LocationDisplay}","arcs":[[52]]},{"type":"Polygon","properties":{"InitiativeTitle":"Promise Zones","LocationDisplay":"Jackson, SD","NumberOfProjects":1,"id":22658219},"popupTemplate":"<strong>{InitiativeTitle}</strong><BR>{LocationDisplay}","arcs":[[53,-21,54]]},{"type":"Polygon","properties":{"InitiativeTitle":"Promise Zones","LocationDisplay":"Jackson, SD","NumberOfProjects":1,"id":22658219},"popupTemplate":"<strong>{InitiativeTitle}</strong><BR>{LocationDisplay}","arcs":[[53,-21,54]]},{"type":"Polygon","properties":{"InitiativeTitle":"Promise Zones","LocationDisplay":"Jasper, SC","NumberOfProjects":1,"id":22657656},"popupTemplate":"<strong>{InitiativeTitle}</strong><BR>{LocationDisplay}","arcs":[[-45,55]]},{"type":"Polygon","properties":{"InitiativeTitle":"Promise Zones","LocationDisplay":"Jasper, SC","NumberOfProjects":1,"id":22657656},"popupTemplate":"<strong>{InitiativeTitle}</strong><BR>{LocationDisplay}","arcs":[[-45,55]]},{"type":"Polygon","properties":{"InitiativeTitle":"Promise Zones","LocationDisplay":"John H. Boner Community Center","NumberOfProjects":1,"id":841},"popupTemplate":"<strong>{InitiativeTitle}</strong><BR>{LocationDisplay}","arcs":[[56]]},{"type":"Polygon","properties":{"InitiativeTitle":"Promise Zones","LocationDisplay":"Kentucky Highlands Investment Corporation","NumberOfProjects":1,"id":850},"popupTemplate":"<strong>{InitiativeTitle}</strong><BR>{LocationDisplay}","arcs":[[57]]},{"type":"Polygon","properties":{"InitiativeTitle":"Promise Zones","LocationDisplay":"Knox, KY","NumberOfProjects":1,"id":22658200},"popupTemplate":"<strong>{InitiativeTitle}</strong><BR>{LocationDisplay}","arcs":[[58,-39,-15,59]]},{"type":"Polygon","properties":{"InitiativeTitle":"Promise Zones","LocationDisplay":"Knox, KY","NumberOfProjects":1,"id":22658200},"popupTemplate":"<strong>{InitiativeTitle}</strong><BR>{LocationDisplay}","arcs":[[58,-39,-15,59]]},{"type":"Polygon","properties":{"InitiativeTitle":"Promise Zones","LocationDisplay":"Leslie, KY","NumberOfProjects":1,"id":22658201},"popupTemplate":"<strong>{InitiativeTitle}</strong><BR>{LocationDisplay}","arcs":[[60,-47,-17,-38]]},{"type":"Polygon","properties":{"InitiativeTitle":"Promise Zones","LocationDisplay":"Leslie, KY","NumberOfProjects":1,"id":22658201},"popupTemplate":"<strong>{InitiativeTitle}</strong><BR>{LocationDisplay}","arcs":[[60,-47,-17,-38]]},{"type":"Polygon","properties":{"InitiativeTitle":"Promise Zones","LocationDisplay":"Letcher, KY","NumberOfProjects":1,"id":22658202},"popupTemplate":"<strong>{InitiativeTitle}</strong><BR>{LocationDisplay}","arcs":[[61,-49]]},{"type":"Polygon","properties":{"InitiativeTitle":"Promise Zones","LocationDisplay":"Letcher, KY","NumberOfProjects":1,"id":22658202},"popupTemplate":"<strong>{InitiativeTitle}</strong><BR>{LocationDisplay}","arcs":[[61,-49]]},{"type":"Polygon","properties":{"InitiativeTitle":"Promise Zones","LocationDisplay":"Los Angeles, CA","NumberOfProjects":1,"id":22172202},"popupTemplate":"<strong>{InitiativeTitle}</strong><BR>{LocationDisplay}","arcs":[[62,63,64,65,66,67,68,69,70,71,72,73,74],[75],[76,77],[78],[79,80,81,82,83],[84],[85],[86]]},{"type":"Polygon","properties":{"InitiativeTitle":"Promise Zones","LocationDisplay":"Los Angeles, CA","NumberOfProjects":1,"id":22172202},"popupTemplate":"<strong>{InitiativeTitle}</strong><BR>{LocationDisplay}","arcs":[[87,63,88,89,66,90,68,91,70,92,72,93,74],[75],[94,77],[78],[95,80,96,97,83],[84],[85],[86]]},{"type":"Polygon","properties":{"InitiativeTitle":"Promise Zones","LocationDisplay":"Minneapolis, MN","NumberOfProjects":1,"id":22271018},"popupTemplate":"<strong>{InitiativeTitle}</strong><BR>{LocationDisplay}","arcs":[[98]]},{"type":"Polygon","properties":{"InitiativeTitle":"Promise Zones","LocationDisplay":"Office of Community Empowerment and Opportunity","NumberOfProjects":1,"id":848},"popupTemplate":"<strong>{InitiativeTitle}</strong><BR>{LocationDisplay}","arcs":[[99]]},{"type":"Polygon","properties":{"InitiativeTitle":"Promise Zones","LocationDisplay":"Office of the Mayor of the City of Camden","NumberOfProjects":1,"id":842},"popupTemplate":"<strong>{InitiativeTitle}</strong><BR>{LocationDisplay}","arcs":[[100]]},{"type":"Polygon","properties":{"InitiativeTitle":"Promise Zones","LocationDisplay":"Oglala Lakota, SD","NumberOfProjects":1,"id":22658210},"popupTemplate":"<strong>{InitiativeTitle}</strong><BR>{LocationDisplay}","arcs":[[-55,-23,101]]},{"type":"Polygon","properties":{"InitiativeTitle":"Promise Zones","LocationDisplay":"Philadelphia, PA","NumberOfProjects":1,"id":22172203},"popupTemplate":"<strong>{InitiativeTitle}</strong><BR>{LocationDisplay}","arcs":[[-29,102,-27,103,-32,104]]},{"type":"Polygon","properties":{"InitiativeTitle":"Promise Zones","LocationDisplay":"Sacramento Housing and Redevelopment Agency","NumberOfProjects":1,"id":846},"popupTemplate":"<strong>{InitiativeTitle}</strong><BR>{LocationDisplay}","arcs":[[105]]},{"type":"Polygon","properties":{"InitiativeTitle":"Promise Zones","LocationDisplay":"Sacramento, CA","NumberOfProjects":1,"id":22271019},"popupTemplate":"<strong>{InitiativeTitle}</strong><BR>{LocationDisplay}","arcs":[[106]]},{"type":"MultiPolygon","properties":{"InitiativeTitle":"Promise Zones","LocationDisplay":"San Antonio, TX","NumberOfProjects":1,"id":22172204},"popupTemplate":"<strong>{InitiativeTitle}</strong><BR>{LocationDisplay}","arcs":[[[107],[108],[109],[110],[111],[112],[113],[114],[115],[116],[117],[118],[119],[120],[121],[122],[123],[124],[125],[126],[127],[128],[129],[130],[131],[132],[133],[134],[-136],[136],[137],[138],[139],[140],[141],[142],[143],[144],[145],[146],[147],[148],[149]]]},{"type":"Polygon","properties":{"InitiativeTitle":"Promise Zones","LocationDisplay":"Southern Carolina Regional Development Alliance","NumberOfProjects":1,"id":843},"popupTemplate":"<strong>{InitiativeTitle}</strong><BR>{LocationDisplay}","arcs":[[150]]},{"type":"Polygon","properties":{"InitiativeTitle":"Promise Zones","LocationDisplay":"St. Louis Economic\nDevelopment Partnership","NumberOfProjects":1,"id":844},"popupTemplate":"<strong>{InitiativeTitle}</strong><BR>{LocationDisplay}","arcs":[[151]]},{"type":"Polygon","properties":{"InitiativeTitle":"Promise Zones","LocationDisplay":"St. Louis, MO","NumberOfProjects":1,"id":22271020},"popupTemplate":"<strong>{InitiativeTitle}</strong><BR>{LocationDisplay}","arcs":[[152]]},{"type":"Polygon","properties":{"InitiativeTitle":"Promise Zones","LocationDisplay":"Thunder Valley Community Development Corporation","NumberOfProjects":1,"id":845},"popupTemplate":"<strong>{InitiativeTitle}</strong><BR>{LocationDisplay}","arcs":[[153]]},{"type":"Polygon","properties":{"InitiativeTitle":"Promise Zones","LocationDisplay":"Whitley, KY","NumberOfProjects":1,"id":22658204},"popupTemplate":"<strong>{InitiativeTitle}</strong><BR>{LocationDisplay}","arcs":[[-60,-20,154]]},{"type":"Polygon","properties":{"InitiativeTitle":"Promise Zones","LocationDisplay":"Whitley, KY","NumberOfProjects":1,"id":22658204},"popupTemplate":"<strong>{InitiativeTitle}</strong><BR>{LocationDisplay}","arcs":[[-60,-20,154]]}]}},"arcs":[[[8166,2464],[9,24],[6,15],[6,-5],[12,-10],[4,-3],[14,-13],[17,0],[5,3],[3,4],[3,-1],[7,3]],[[8252,2481],[5,-18],[15,-28],[4,-13]],[[8276,2422],[-32,-53],[-1,-24],[-1,1],[-3,-3],[-3,-7],[-1,0],[0,-1],[3,-33],[-13,-30],[-1,-4],[-2,-10],[-5,-5],[-6,-10],[-2,0]],[[8209,2243],[0,1],[0,1],[0,1],[-1,0],[0,-1],[-1,0],[-1,0],[0,1],[0,1],[0,1],[1,0],[1,0],[0,1],[0,1],[0,-1],[-1,0],[0,1],[0,1],[0,1],[1,2],[-1,1],[0,-1],[0,-1],[-1,0],[0,1],[0,1],[1,0],[0,1],[-1,0],[0,1],[0,1],[-1,0],[0,-1],[-1,0],[0,1],[-1,0],[0,1],[1,1],[1,0],[0,1],[1,-1],[0,1],[1,1],[0,1],[0,1],[0,1],[-1,0],[0,-1],[-1,0],[-1,1],[0,1],[0,1],[0,1],[0,-1],[1,0],[0,1],[0,1],[-1,0],[0,1],[0,1],[1,0],[0,1],[1,1],[0,1],[-1,0],[0,1],[0,1],[0,1],[-1,0],[0,1],[0,1],[1,0],[0,1],[0,1],[0,1],[0,1],[0,1],[0,1],[0,-1],[1,1],[0,1],[0,1],[0,2],[-1,0],[0,-1],[-1,0],[0,1],[0,1],[1,0],[0,1],[0,1],[0,1],[0,1],[-1,0],[0,1],[0,1],[1,-1],[1,1],[0,1],[0,2],[0,1],[-1,0],[0,1],[0,1],[0,1],[-1,1],[-1,1],[0,-1],[-1,-1],[0,1],[-1,1],[0,1],[0,1],[0,1],[0,1],[0,1],[-1,-1],[0,-1],[-1,-1],[0,-1],[0,-1],[-1,1],[0,1],[1,0],[-1,1],[0,1],[0,2],[1,1],[0,3],[0,1],[0,1],[0,1],[0,1],[0,1],[0,1],[0,2],[0,1],[-1,0],[0,1],[-1,1],[0,2],[0,1],[-1,0],[0,-1],[0,-1],[0,-1],[-1,0],[-1,1],[0,1],[0,1],[0,1],[0,2],[0,1],[1,0],[0,1],[0,1],[1,0],[0,-1],[0,1],[0,1],[0,1],[1,0],[0,1],[0,1],[0,1],[-1,1],[-1,0],[0,-1],[0,-1],[0,-1],[1,0],[0,-1],[-1,0],[0,1],[0,1],[-1,0],[-1,1],[0,1],[1,1],[0,1],[0,1],[0,1],[-1,1],[0,1],[1,1],[0,1],[0,1],[-1,0],[-1,0],[0,1],[0,1],[1,0],[0,1],[0,1],[0,1],[-1,1],[0,1],[0,1],[-1,0],[0,1],[0,1],[0,1],[-1,0],[-1,1],[0,1],[0,1],[0,1],[0,1],[0,1],[1,1],[0,1],[-1,0],[0,1],[0,1],[-1,1],[0,1],[0,1],[0,1],[-1,2],[0,1],[0,1],[0,1],[0,1],[0,1],[0,1],[0,1],[1,0],[0,-1],[0,-1],[0,-1],[1,0],[0,-1],[0,1],[1,0],[0,1],[0,3],[0,2],[0,1],[0,1],[1,1],[0,1],[0,1],[-1,0],[0,1],[1,1],[0,1],[-1,1],[0,1],[0,1],[1,0],[0,1],[0,1],[0,1],[0,1],[0,1],[-1,0],[0,1],[-1,0],[0,1],[0,1],[1,0],[0,1],[1,0],[0,1],[0,1],[0,1],[-1,0],[0,1],[0,1],[-1,0],[0,1],[0,1],[-1,0],[0,-1],[0,-1],[0,-1],[0,-1],[-1,0],[0,1],[0,1],[1,1],[0,2],[-1,2],[-1,0],[0,1],[0,1],[1,0],[0,1],[0,1],[0,1],[-1,0],[-1,1],[-1,3],[0,1],[0,2],[-1,0],[-1,-1],[-1,1],[0,3],[0,1],[0,1],[-1,0],[-1,-1],[0,-1],[-1,-1],[-1,1],[-1,1],[0,2],[1,0],[0,1],[1,1],[0,1],[0,1],[-1,1],[0,1],[0,1],[-1,0],[0,-1],[0,-1],[0,-1],[0,-1],[-1,0],[0,1],[-1,2],[0,1],[0,1],[0,1],[0,1],[-1,0],[0,2],[-1,0],[0,1],[0,1],[-1,0],[-1,0],[-1,1],[0,1],[0,1],[0,1],[1,1],[0,1],[-1,1],[0,1],[0,1],[-1,-1],[0,-1],[0,-1],[-1,0],[0,-1],[0,1],[0,1],[0,2],[0,1],[0,1],[0,2],[0,1],[-1,1]],[[5144,3134],[1,164]],[[5145,3298],[52,-2],[0,58],[11,0],[1,0],[-1,53],[0,56]],[[5208,3463],[22,0],[22,1],[0,-2],[0,-54],[22,0],[20,0],[0,-55],[-22,1],[0,-221]],[[5272,3133],[-43,1]],[[5229,3134],[-42,1],[-1,-1],[-42,0]],[[5237,3371],[0,-3],[2,0],[0,2],[-1,0],[0,1],[-1,0]],[[8247,2680],[2,0],[4,-17],[6,-1],[10,-18],[6,-2],[8,-20],[3,0],[17,-25],[12,-29],[8,-14],[3,-23],[7,-16]],[[8333,2515],[-19,-31],[1,-14],[1,-9],[-3,-10],[-1,-11],[-1,0],[-1,6],[-5,22],[-2,-2],[-27,-44]],[[8252,2481],[-3,7],[-1,9],[-2,6],[1,40],[-1,5],[2,102],[-1,12],[0,18]],[[8166,2464],[-1,0],[-1,-1],[-1,-1],[-1,0],[-1,0],[-1,0],[0,1],[-1,0],[-1,2],[-1,2],[0,2],[-1,1],[-1,1],[-1,2],[-2,2],[-3,2],[-1,0],[0,1],[-1,1],[0,1],[-1,1],[-1,1],[0,1],[-1,0],[0,1],[-1,2],[0,2],[-1,2],[-2,2],[0,1],[-1,3],[-1,3],[-1,3],[-1,2],[-1,4],[0,3],[0,1],[0,2],[-1,2],[0,1],[1,1],[0,1],[0,1],[0,1],[0,1],[1,1],[0,1],[1,1],[0,1],[0,2],[0,1],[49,116],[29,68],[7,-5],[3,1],[4,-3],[7,-10],[5,-12],[6,-4]],[[7704,4728],[-1,2],[1,2],[1,3],[0,4],[1,5],[0,1],[1,-2],[1,-4],[2,2],[1,2],[2,5],[0,2],[0,3],[0,4],[1,4],[0,2],[3,1],[1,2],[0,1],[0,3],[-1,2],[1,3],[2,4],[0,12],[2,8],[1,1],[3,1],[2,-1],[1,2],[0,-1],[1,-2],[1,-1],[1,6],[3,4],[1,3],[2,3],[1,3],[-1,4],[1,0],[1,0],[3,0],[0,1],[-1,4],[2,6],[0,1],[3,6],[3,-1],[2,3],[0,5],[0,2],[1,5],[1,1],[2,0],[2,4],[1,1],[1,1],[0,2],[3,3],[1,2],[2,3],[-1,6],[1,3],[1,0],[0,3],[0,4],[-1,1],[-2,1],[-2,6],[1,3]],[[7763,4897],[12,-8],[1,-4],[3,1]],[[7779,4886],[0,-9],[1,-1],[1,-2],[2,-4],[0,-1],[-2,-1],[-1,-3],[0,-4],[1,-2],[1,0],[1,0]],[[7783,4859],[-1,-5],[0,-11],[0,-4],[1,-5],[2,-5],[-6,-26],[0,-2],[3,-9],[2,-4],[-1,-18],[-1,-4],[-1,-9],[2,-9],[1,-6],[0,-1],[1,0],[4,-7],[0,-5],[0,-16]],[[7789,4713],[-1,0],[-3,1],[-2,1],[-1,2],[-1,0],[0,-1],[-1,0],[-1,0],[-1,0],[0,-1],[-3,-1],[-1,0],[0,-1],[0,-1],[-2,-4],[-1,-1],[-1,-1],[-2,-1],[0,-2],[-1,-2],[-2,-2],[-1,0],[-4,-3],[-1,0],[-1,-2],[-1,-2],[0,-1],[-1,-1],[-1,-2],[-2,-1],[-1,1],[-1,0],[0,-1],[-1,-4],[-1,-3],[-1,-3],[-1,-1],[-1,0],[-1,-1],[0,-2],[0,-1],[0,-1],[0,-1],[-1,-1],[0,-1],[-1,-4],[-1,-1],[0,-1],[-20,0],[-22,2],[-7,1]],[[7693,4665],[0,6],[1,2],[0,1],[-2,11],[-1,6],[-3,6],[0,2],[1,5],[2,3],[3,4],[2,0],[8,12],[0,5]],[[3978,8951],[50,0],[24,1],[48,-1],[59,0]],[[4159,8951],[0,-246],[-42,-1],[-13,0],[-7,0],[-19,0],[-18,0],[-28,2],[-47,0]],[[3985,8706],[-1,81],[-5,0],[-1,55],[0,109]],[[5229,3134],[0,-2],[2,-3],[1,0],[1,1],[1,-1],[0,-2],[1,1],[1,0],[0,-1],[1,-1],[0,-1],[1,-1],[-1,-2],[0,-1],[1,-1],[0,-2],[0,-1],[0,-1],[0,-1],[0,-1],[1,-1],[1,0],[0,-2],[0,-6],[0,-27],[0,-13],[0,-62],[0,-4],[2,-7],[2,-5],[2,-2],[3,-1],[2,-2],[2,-4],[1,-6],[1,-8],[1,-2],[3,-7],[3,0],[2,-1],[2,-2],[2,1],[1,1],[2,-1],[1,0],[0,1],[1,1],[3,-1]],[[5276,2954],[1,-2],[1,-3],[0,-2],[0,-2],[0,-2],[-1,-2],[-1,-3],[-1,-1],[-1,1],[-1,1],[0,1],[-1,2],[0,1],[-1,1],[-1,2],[-1,1],[-1,0],[-1,0],[-2,-1],[-1,-1],[0,-1],[0,-1],[0,-3],[0,-2],[0,-3],[0,-1],[-1,-2],[0,-1],[-2,-1],[-1,1],[-1,1],[0,1],[0,2],[-1,1],[-1,2],[0,1],[-1,1],[0,1],[0,1],[-1,1],[-2,2],[-2,3],[-1,2],[-1,3],[-1,1],[-1,1],[-1,2],[-1,1],[-1,2],[-1,1],[0,1],[-1,0],[-1,-1],[0,-2],[-1,-2],[0,-2],[0,-3],[0,-2],[-1,-3],[-1,-1],[0,-1],[-1,0],[-1,0],[-1,-1],[-1,0],[-1,-1],[-1,0],[-1,-1],[-1,-1],[-1,-2],[-2,-1],[-1,-1],[-1,-1],[0,-1],[-1,0],[0,1],[0,1],[0,2],[0,3],[0,1],[0,1],[0,2],[0,1],[0,1],[-1,1],[-1,0],[-1,-2],[0,-3],[0,-2],[0,-2],[0,-1],[0,-2],[-1,-2],[-1,-2],[0,1],[-1,1],[-1,-1],[-1,0],[-1,-2],[-1,0],[-1,1],[-1,1],[0,2],[0,1],[-1,1],[-1,2],[0,2],[0,1],[-1,1],[-1,0],[0,-1],[0,-2],[0,-1],[1,-1],[0,-2],[0,-3],[0,-2],[0,-1],[-1,-1],[0,1],[-1,1],[0,1],[-1,0],[-1,-1],[0,-1],[-1,-3],[0,-1],[-1,-2],[-1,-1],[-1,0],[-1,0],[-1,-1],[-1,-2],[-1,-1],[-1,-2],[-1,-1],[-1,-1],[0,-2],[-1,-3],[0,-3],[0,-2],[0,-3],[0,-3],[0,-4],[0,-3],[0,-3],[-1,-3],[-1,-2],[0,-2],[-2,-2],[-2,-3],[-1,0],[-2,0],[-1,0],[-1,0],[0,-1],[-1,0],[-1,0],[-1,2],[0,2],[-1,1],[-1,0],[-1,1],[-1,1],[0,1],[-1,2],[-1,1],[-2,1],[-1,1],[-2,0],[0,-1],[-1,-1],[-1,-3],[0,-5],[-1,-3],[0,-2],[0,-2],[-1,-2],[0,-3],[0,-2],[1,-4],[-1,-3],[0,-3],[0,-5],[-1,-3],[0,-2],[-1,-1],[-1,-1],[-1,-2],[-1,-2],[-1,-2],[-1,-1],[-1,0],[-1,0],[0,2],[-1,0],[0,4],[0,2],[0,2],[0,2],[-1,3],[0,3],[-1,1],[0,1],[0,1],[-1,2],[-1,1],[0,1],[-1,2],[-1,4],[-3,6],[0,2],[-1,3],[-1,2],[0,2],[0,3],[-1,2],[0,3],[-1,1],[0,1],[-1,1],[0,1],[-2,1],[-1,0],[-1,0],[-2,0],[-1,0],[-1,0],[-1,-1],[-1,-2],[-2,-1],[-1,-1],[-1,0],[-1,1],[-1,1],[0,2],[-1,2],[0,2],[-1,2],[0,2],[0,2],[0,2],[0,2],[0,3],[0,1],[-1,3],[0,2],[0,1],[-1,2],[-1,1],[0,1],[-1,0],[0,-1],[-2,-1],[-1,0],[-1,0],[-1,0],[0,-1],[-1,0],[-1,-1],[0,1],[-1,0],[-1,2],[-1,2],[-6,8],[-1,3],[-1,3],[0,4],[1,5],[2,7],[2,4],[1,2],[1,3],[0,3],[0,2],[0,2],[0,5],[1,3],[0,2],[-1,2],[0,2],[0,1],[0,1],[0,2],[-1,2],[0,3],[0,3],[0,2],[0,3],[0,3],[0,1],[1,1],[1,1],[1,2],[0,1],[0,3],[-1,3],[-1,2],[-2,0],[-1,2],[-1,4],[1,1],[-1,2],[-1,1],[-1,3],[0,2],[0,1],[-1,3],[0,1],[-1,3],[-1,1],[1,1],[1,-1],[1,1],[0,1],[1,1],[0,-1],[1,1],[0,1],[1,2],[1,1],[0,-1],[1,-2],[1,-2],[2,-1],[1,3],[0,1],[0,2],[-2,3],[0,2],[1,6],[-1,5],[0,3],[1,0],[1,-2],[1,-2],[1,1],[0,2],[1,2],[0,5],[1,2],[1,2],[0,2],[-1,2],[-1,-2],[0,1],[-1,0],[0,1],[0,1],[0,1],[1,0],[0,-1],[1,0],[0,1],[0,1],[0,1],[-1,-1],[-1,0],[0,1],[0,1],[-1,0],[0,1],[0,1],[1,0],[0,1],[0,1],[-1,0],[0,1],[0,1],[0,1],[0,1],[-1,0],[0,1],[0,1],[-1,0],[0,1],[0,1],[0,1],[-1,0],[0,1],[1,0],[0,1],[0,1],[0,1],[-1,0],[0,1],[0,1],[6,0],[10,-8],[-2,8],[12,0],[0,28],[10,0]],[[9490,6786],[0,0]],[[9490,6786],[0,0]],[[9490,6786],[0,0]],[[9490,6786],[0,1],[0,1],[0,1],[1,0],[0,1],[1,1],[0,1]],[[9492,6792],[0,-1],[1,-1],[1,0],[1,-1],[1,1],[1,2],[1,2],[1,1],[0,1],[1,-1],[0,-1],[0,-1],[1,-2],[0,-1],[0,-1],[0,-1],[1,-1],[0,1],[1,0],[0,-1],[0,-1],[0,-1],[-1,0],[0,-1],[0,-1],[1,0],[1,0],[0,-1],[-1,0],[0,-1],[-1,-1],[0,-1],[0,-1],[-1,-1],[0,1],[-1,0],[0,-1],[0,-1],[-1,0],[0,-1],[0,-1],[1,1],[0,-1],[0,-1],[0,-1],[0,-1],[0,-1],[0,-1],[0,-1],[0,-1],[-1,0],[0,-1],[-1,-1],[-1,0],[0,-1],[0,-1],[0,-1],[0,-1],[1,0],[0,-1],[0,-1],[1,-1],[-1,0],[0,-1],[0,-1],[0,-1],[0,-1],[0,-1]],[[9498,6753],[-1,-1],[-1,0],[0,1],[-1,0],[0,-1],[-1,0],[0,1],[0,1],[0,1],[0,-1],[0,1],[0,1],[0,1],[0,-1],[0,-1],[0,1],[0,1],[-1,1],[-1,-1],[-1,0]],[[9491,6757],[0,1],[0,1],[0,2],[0,1],[0,1],[0,1],[0,1],[-1,1],[0,1],[0,2],[0,1],[0,1],[0,2],[0,1],[0,1],[0,1],[0,1],[0,1],[0,1],[0,1],[0,1],[0,1],[0,1],[0,1],[0,1],[0,1]],[[5547,3907],[-1,-126],[-10,3],[0,-4],[-7,-2],[0,-3],[-6,-1],[2,13],[0,10],[1,7],[-3,-8],[-4,-1],[-3,-7],[-2,0],[-3,-7],[-3,7],[-4,-3],[-3,-18],[1,-18],[3,-9],[5,4],[1,-13],[3,-7],[4,-6],[0,-24],[-2,-1],[-1,-5],[3,-1],[0,-5],[-3,-18],[-3,0],[-3,2],[-1,-6],[-1,2],[-3,-6],[-1,-8],[4,-8],[0,6],[38,-1],[-3,-217],[-3,-213],[-1,-154],[-1,-156],[-1,-98],[-10,2],[-1,14],[-6,7],[-4,10],[-2,-13],[-3,10],[-5,9],[-10,-7],[-5,16],[-9,29],[-6,0],[1,-10],[-6,-6],[0,21],[-5,2],[0,-19],[-6,5],[1,17],[-5,-2],[-6,10],[2,23],[-6,4],[-6,10],[-2,10],[-6,3],[-7,-3],[-2,17],[-2,15],[-5,4],[-8,-8],[-1,23],[-3,-4],[-18,18],[-2,-8],[-4,-11],[0,-17],[-5,1],[-1,-19],[-8,6],[-4,-8],[-13,-6],[-8,5],[-4,12],[-6,-10],[-2,14],[-6,-10],[-3,29],[-10,9],[-3,-10],[-5,-12],[-6,-1],[-4,-12],[-12,7],[-4,-16],[-14,0],[-5,11],[-4,18],[-7,5],[-4,10],[0,113],[-2,3],[-1,11],[-8,6],[-69,0],[0,-19],[-10,1],[1,-14],[0,-13],[1,-4],[0,-10],[3,-4],[1,-5],[-3,-9],[-2,-21],[-2,-12],[-5,-18],[-5,-1],[1,9],[-6,1],[0,119],[9,-1],[0,165],[-21,1],[0,164],[21,0],[0,55],[64,0],[0,27],[2,-10],[-1,-72],[43,0],[0,-55],[26,1],[6,35],[-8,32],[2,6],[1,10],[-2,3],[2,12],[0,6],[2,9],[0,24],[-20,0],[-2,-13],[-1,-23],[-9,0],[-1,18],[-11,-17],[-13,0],[-1,34],[2,-1],[0,28],[2,0],[1,9],[3,0],[0,9],[11,0],[1,4],[5,5],[6,0],[7,16],[-3,29],[3,7],[6,2],[0,11],[4,-1],[1,7],[4,4],[3,3],[3,6],[3,5],[5,-5],[5,12],[2,27],[11,28],[2,9],[3,-4],[12,1],[0,-7],[10,3],[3,11],[22,1],[0,-61],[36,-3],[3,6],[5,5],[5,6],[-1,16],[-4,5],[-3,-2],[2,8],[0,16],[-1,34],[-12,0],[1,31],[-4,2],[0,11],[5,17],[6,-2],[0,12],[-3,13],[5,5],[2,-2],[2,9],[0,8],[4,0],[3,12],[9,26],[5,2],[5,-15],[8,-9],[9,-6],[1,-24],[5,-7],[12,16],[2,-24],[8,-2],[5,19],[7,-1],[6,-16],[4,-9],[1,-10],[9,-6],[6,18],[3,8],[3,-4],[4,-12],[5,1],[2,1],[4,-2],[2,1],[3,6],[-2,8],[-1,10],[2,7],[-1,10],[4,4],[5,2],[1,5]],[[5272,3133],[43,0],[15,0],[6,0],[9,0],[3,0],[11,0],[41,0],[0,-138],[-1,1],[-1,2],[-1,2],[-2,2],[-2,1],[-2,2],[0,2],[-1,1],[-1,2],[-1,0],[-1,1],[-1,0],[-1,-1],[0,-2],[0,-2],[-1,-2],[0,-1],[-1,-1],[-1,-1],[-1,-3],[-1,-3],[0,-3],[0,-2],[1,-5],[0,-4],[0,-3],[0,-4],[-1,-3],[0,-3],[-1,-3],[-1,-2],[0,1],[0,1],[0,2],[0,4],[0,2],[0,2],[-1,2],[0,1],[-1,0],[-1,0],[-1,-1],[-1,-1],[0,-2],[1,-2],[0,-3],[1,-2],[0,-3],[0,-1],[0,-1],[0,-4],[0,-1],[-1,-2],[-2,-1],[0,1],[-1,0],[-2,0],[-1,2],[0,1],[0,3],[-1,2],[0,1],[-1,1],[-1,0],[-1,-2],[0,-3],[-1,-3],[0,-1],[-2,-1],[-2,-1],[0,-2],[-1,-2],[-1,0],[-1,1],[-1,1],[-1,1],[-1,-2],[-2,-2],[-1,-1],[-1,0],[-1,1],[-1,2],[-1,2],[-1,1],[0,-1],[-1,-3],[-1,-1],[-1,0],[-1,1],[-1,2],[0,1],[0,2],[-1,2],[0,3],[-1,2],[0,1],[-1,1],[-1,-1],[-1,-3],[-1,-2],[-3,-2],[-1,0],[-1,0],[-1,0],[0,2],[1,1],[-1,2],[1,4],[0,3],[-1,1],[0,1],[-1,0],[-1,-1],[-1,-4],[0,-2],[-1,-2],[-1,-2],[-1,0],[-1,0],[-1,0],[-1,3],[0,3],[0,2],[1,2],[0,3],[0,3],[-1,4],[0,2],[0,3],[0,3],[-1,2],[0,1],[-1,1],[-1,1],[-1,0],[-1,0],[-1,0],[-1,3],[-1,3],[-1,0],[0,-2],[0,-2],[0,-2],[-1,-1],[-1,0],[-1,0],[-1,-3],[-1,-3],[-1,-4],[0,-2],[-1,-3],[0,-2],[-1,0],[-1,0],[-1,2],[-1,1],[-1,1],[-2,-1],[-1,-1],[-1,-4],[-1,-3],[-1,-3],[-1,-2],[-2,-1],[-1,-1],[-2,0],[-1,3],[-1,2],[-1,1],[-2,1],[-1,0],[-1,0],[-1,-1],[-1,-2],[0,-3],[-1,-4],[0,-2],[0,-2],[0,-1]],[[670,3100],[3,0],[0,-9],[1,0],[0,-17],[1,0],[2,-3],[0,-2],[-1,0],[-1,-5],[-3,0],[0,23],[-1,1],[-1,0],[0,1],[-1,0],[0,2],[-5,0],[0,1],[2,0],[0,4],[-1,0],[0,3],[-1,0],[0,1],[2,0],[0,1],[1,0],[0,-3],[0,-2],[2,0],[-1,2],[2,0],[0,2]],[[5776,9972],[1,0],[0,3],[0,2],[0,13],[2,0],[1,0],[0,-1],[0,1],[1,0],[1,0],[0,-3],[1,-5],[1,-7],[0,-5],[0,-4],[0,-4],[-2,0],[-1,-2],[0,-1],[0,-1],[0,-1],[1,-3],[0,-1],[-1,-1],[-1,0],[-1,0],[-1,0],[0,1],[-1,0],[0,2],[0,9],[0,1],[0,5],[-1,1],[0,1]],[[4721,163],[1,2],[0,-1],[0,-1],[1,0],[0,-1],[2,0],[0,-1],[1,0],[0,2],[1,0],[1,0],[0,-2],[0,-1],[1,0],[1,7],[1,2],[0,1],[3,0],[1,6],[-1,0],[0,1],[0,1],[1,3],[0,1],[0,2],[3,0],[0,3],[1,0],[0,3],[2,0],[0,-2],[0,-1],[0,-1],[1,0],[0,-3],[-6,-10],[0,-5],[0,-2],[1,-1],[1,-3],[1,-3],[0,-4],[0,-27],[0,-2],[-3,0],[0,1],[-1,0],[-1,1],[-1,1],[-3,4],[-3,1],[0,-5],[-5,0],[0,19],[-1,1],[-1,1],[0,3],[1,3],[0,1],[0,2],[0,1],[0,1],[0,2]],[[7779,5074],[-4,-3],[5,-17],[-10,-24],[0,-30],[4,-10],[-4,-16],[1,-1],[1,-6],[-1,-13],[2,0],[1,-5],[2,-8],[1,-4],[1,-2],[1,-5],[0,-3],[-2,-2],[-1,-1],[1,-6],[0,-3],[0,-2],[2,-27]],[[7763,4897],[-2,-1],[-2,-1],[-1,2],[0,2],[-1,2],[-1,-1],[-3,1],[-4,6],[-2,3],[-2,3],[-1,1],[-3,2],[-2,4],[-1,2],[-1,1],[-2,3],[-1,4],[-1,7],[-2,5],[-1,-1],[-3,-2],[-2,-5],[-1,2],[0,3],[0,4],[1,1],[0,4],[-1,0],[-2,0],[-2,0],[-1,-2],[-1,-3],[-1,-1],[-2,-1],[-2,3],[1,6],[-1,2],[-1,-2],[-1,0],[-3,1],[0,2],[0,3],[0,3],[-2,0],[-1,0]],[[7705,4959],[0,3],[-1,2],[-1,0],[0,3],[-1,4],[1,3],[1,3],[2,1],[1,5],[-1,7],[-1,2],[-1,0],[-1,1],[0,2],[0,1],[-1,4],[-2,-2],[-1,-3],[-1,-1],[0,2],[-2,-1],[-1,-1],[-1,1],[-1,3],[0,2],[-1,2],[1,4],[-1,6],[-1,2],[-2,6],[-2,6],[-1,3],[-1,1],[0,5],[2,2],[1,6],[1,5],[2,3],[0,3],[-1,28],[1,2],[0,4],[4,1],[2,-3],[2,-1],[0,2],[1,3],[-1,3],[1,2],[1,3],[1,5],[0,2],[2,5],[0,4],[-1,1],[0,3],[4,0],[8,15],[5,0],[1,0],[2,3],[0,5],[0,4],[7,-4],[6,-3],[7,-1],[1,0],[1,1],[0,5],[2,6],[3,1],[0,-4],[1,-3],[1,0],[1,-2],[1,-5],[0,-3],[2,-3],[0,-7],[1,-1],[1,-4],[1,1],[0,-4],[2,-4],[1,-1],[2,1],[0,-2],[2,-7],[0,-3],[2,-1],[-1,-5],[0,-1],[1,0],[1,2],[1,-1],[1,-1],[2,-2],[1,-4],[1,0],[0,2],[2,-2],[1,-3],[1,-5],[0,-4]],[[5145,3298],[-10,0],[-13,0],[0,54],[1,0],[-1,110],[22,0],[0,56],[21,0],[43,0],[0,-55]],[[8333,2515],[10,-1],[5,-7],[6,-14],[4,-20],[11,-26],[7,-7],[11,8],[4,-8],[10,5],[1,-1],[4,-8],[1,1],[7,1],[3,-8],[0,-6],[-4,-10],[0,-12],[-2,-14],[1,-13],[2,-14],[1,-3],[-1,-8],[0,-6],[3,-9],[-2,-5],[-1,-16],[1,-8],[-3,-24],[-5,-9],[0,-9],[-3,-12],[0,-14],[1,-6],[4,-5],[2,-17],[-1,-4],[1,-5],[-1,-3],[0,-2],[1,-2],[0,-3],[1,-2],[1,-3],[0,-1],[1,-1],[1,2],[1,0],[1,-3],[-1,-2],[-1,-2],[-1,-1],[-1,-9],[-1,-1],[-2,1],[-1,-1],[0,-1],[0,-1],[0,-9],[0,-1],[1,-1],[0,-1],[1,1],[0,1],[1,4],[2,2],[1,2],[1,0],[1,-1],[0,-1],[0,-2],[0,-2],[-2,-7],[0,-2],[0,-1],[0,-3],[1,-3],[0,-1],[0,-5],[0,-3],[0,-2],[0,-1],[0,-1],[-1,-2],[-2,0],[0,-1],[-2,-1],[0,-2],[-1,-3],[0,-2],[1,-2],[1,-2],[0,-1],[1,0],[1,-1],[1,0],[2,-1],[0,-2],[1,-1],[1,-2],[1,-2],[1,-6],[1,-1],[0,-2],[2,-4],[0,-2],[1,-2],[1,0],[0,-1],[1,-2],[1,0],[1,0],[0,1],[1,2],[0,2],[0,1],[0,1],[-1,0],[0,1],[0,1],[-1,1],[0,1],[0,1],[0,1],[-1,1],[-1,0],[0,1],[0,1],[-1,0],[-1,1],[1,1],[0,1],[0,1],[0,1],[0,-1],[1,0],[0,-1],[0,1],[0,-1],[1,0],[0,1],[0,1],[1,0],[0,-1],[0,-1],[1,0],[0,1],[1,0],[0,-1],[1,-1],[-1,0],[0,-1],[1,0],[0,-1],[0,1],[0,-1],[0,-1],[0,-1],[0,1],[0,-1],[-1,-1],[1,-1],[1,0],[0,1],[2,4],[1,1],[1,3],[0,1],[1,0],[0,1],[1,1],[1,-4],[0,-1],[0,1],[1,0],[1,2],[-1,0],[1,0],[0,-1],[0,1],[1,0],[0,1],[0,1],[0,1],[0,1],[0,-1],[1,0],[0,2],[0,1],[1,0],[0,-1],[0,-2],[4,-12],[-3,-6],[-6,-12],[-5,-12],[-12,-44],[-19,52],[-6,6],[-1,2],[-1,0],[-2,5],[0,2],[0,2],[-1,4],[-1,0],[0,2],[-1,3],[-1,1],[-1,1],[-1,3],[0,1],[-1,1],[0,6],[-1,3],[0,5],[-1,8],[-1,0],[-1,-1],[0,-1],[0,-3],[-1,-1],[-1,0],[0,3],[0,5],[0,1],[-2,-1],[-1,1],[-1,1],[2,7],[0,1],[-1,3],[-1,1],[-3,-4],[0,1],[-1,5],[-1,0],[-2,-6],[-1,2],[-1,5],[-3,2],[-3,12],[0,2],[1,5],[0,2],[-1,1],[-1,-4],[-1,0],[-1,1],[0,4],[1,2],[2,0],[0,2],[0,4],[-1,1],[-2,-2],[-1,1],[-1,7],[0,4],[1,1],[2,-1],[0,3],[0,2],[-1,2],[-2,0],[-1,-3],[-3,-2],[0,1],[0,2],[-1,2],[-1,0],[-1,5],[-1,-1],[-1,-1],[-1,2],[-1,1],[0,-2],[-1,-3],[-2,0],[-1,3],[-2,0],[-2,1],[-1,1],[-2,2],[-2,1],[-1,1],[-1,4],[-2,1],[0,1],[-1,1],[0,3]],[[8327,2220],[-4,13],[-1,9],[-2,7],[-1,10],[-2,11],[-4,13],[-1,11],[-2,10],[-7,20],[-3,2],[-2,8],[-3,9],[-7,34],[-5,20],[-2,1],[-1,17],[-4,7]],[[8327,2220],[-2,-3],[-1,-1],[-1,-4],[-1,-4],[-2,-9],[-1,-4],[-1,-2]],[[8318,2193],[0,-4],[-3,-11],[-3,-13],[-12,16],[0,4],[2,6],[1,16],[-1,2],[-1,1],[-2,2],[-1,5],[-1,2],[-1,3],[-1,6],[-6,20],[-16,-37],[-14,-31],[-9,-20],[-4,-6],[-12,-30]],[[8234,2124],[0,-1],[-1,-1],[0,-1],[-1,0],[0,1],[1,0],[0,1],[0,1],[0,1],[0,2],[-1,1],[0,-1],[0,-1],[0,-1],[0,-1],[0,-1],[-1,-1],[0,1],[0,1],[0,1],[0,2],[0,1],[-1,0],[-1,-1],[-2,-1],[-1,0],[-1,0],[0,1],[-4,5],[-2,1],[0,1],[-1,1],[0,1],[1,0],[0,1],[0,1],[0,1],[0,1],[-1,0],[0,-1],[0,-1],[0,-1],[-1,0],[0,1],[0,1],[0,1],[0,1],[0,1],[0,-1],[-1,1],[0,1],[0,1],[0,1],[0,1],[0,1],[-1,0],[0,-1],[0,-1],[0,-1],[-1,1],[-1,2],[-1,2],[0,2],[-1,1],[0,1],[0,1],[0,1],[-1,1],[0,1],[-1,1],[0,1],[0,1],[0,1],[-1,1],[0,1],[-1,1],[0,1],[0,1],[0,1],[0,1],[-1,1],[0,1],[0,1],[0,1],[0,1],[0,1],[1,1],[0,-1],[0,-1],[1,0],[0,-1],[0,-1],[0,1],[1,0],[0,1],[0,1],[0,1],[0,1],[-1,0],[-1,1],[0,1],[1,0],[1,0],[0,1],[1,1],[0,1],[0,1],[1,0],[0,1],[0,1],[0,1],[0,1],[-1,1],[-1,0],[0,1],[0,1],[-1,1],[1,1],[0,-1],[0,-1],[1,-1],[0,1],[1,1],[-1,1],[0,1],[-1,1],[0,1],[0,1],[0,1],[0,1],[1,2],[0,1],[0,1],[0,1],[0,1],[-1,0],[0,1],[0,1],[0,1],[0,1],[0,1],[0,1],[-1,1],[0,1],[0,1],[0,1],[0,-1],[0,-1],[0,-1],[-1,0],[0,1],[0,1],[-1,0],[0,1],[0,1],[0,1],[-1,0],[-1,0],[0,1],[1,1],[0,1],[0,1],[0,1],[0,1],[1,1],[1,0],[0,1],[0,1],[0,1],[-1,1],[0,1],[0,1],[1,0],[1,0],[0,1],[-1,0],[0,1],[-1,0],[0,1],[0,1],[1,0],[0,1],[-1,0],[0,1],[0,1],[1,0],[1,1],[-1,0],[0,1],[0,1],[0,1],[1,0],[0,1],[1,0],[0,1],[0,1],[0,1]],[[7783,4859],[2,0],[1,0],[0,-2],[2,-3],[2,-3],[2,4],[2,3],[1,-4],[4,2],[1,1],[2,4],[0,3],[-1,5],[0,3],[1,3],[3,3],[11,9],[8,8],[3,5],[3,5],[4,10],[2,7],[0,4],[1,2],[2,0],[1,-1],[1,0],[2,5],[2,-4],[1,5],[0,5]],[[7846,4938],[3,0],[1,0],[4,-5],[4,-5],[0,-3]],[[7858,4925],[-1,-3],[-1,-3],[-3,-4],[0,-2],[-1,-6],[0,-9],[0,-2],[2,2],[3,1],[5,6],[13,10],[3,-3],[1,-1],[1,5],[2,4],[1,1],[1,1],[1,1],[1,0],[3,2],[1,0],[2,5],[3,5],[6,-10],[9,-17]],[[7910,4908],[0,-5],[0,-2],[1,-3],[1,-1],[0,-1],[1,0],[0,-1],[-1,-2],[0,-2],[-1,-1],[0,-4],[1,-1],[0,-3],[0,-2],[0,-1],[0,-1],[-1,-1],[0,-1],[0,-1],[-1,-2],[-1,-3],[0,-1],[-1,-1],[0,-1],[1,-3],[1,-1],[0,-1],[-1,-2],[-1,-1],[0,-1],[0,-1],[0,-1],[0,-1],[-1,-1],[-1,-1],[0,-1],[-1,-2],[-1,0],[-2,-1],[0,-1],[0,-1],[0,-1],[-1,-1],[-2,0],[-3,-4],[-3,-1],[-2,-2],[0,-1],[-1,0],[0,-1],[-1,-1],[0,1],[-2,0],[-2,0],[-2,-2],[-1,-2],[0,-1],[0,-2],[-1,-1],[-2,2],[-1,1],[0,2],[0,1],[-4,-1],[0,-1],[-1,-1],[-1,0],[-1,2],[-1,-2],[-1,1],[-1,1],[0,-3],[0,-3],[0,-3],[-1,0],[-2,-1],[0,-2],[0,-1],[-1,0],[-1,-1],[-1,-2],[0,-1],[0,-1],[1,-1],[0,-1],[0,-5],[0,-1],[-1,-4],[-1,-3],[0,-1],[-1,0],[0,-3],[-1,-4],[-1,-2],[-1,-1],[-1,-2],[1,-3],[0,-1],[0,-3],[-1,-2],[0,-1],[0,-1],[1,-2],[0,-2],[0,-1],[0,-3],[-1,-1],[0,-2],[-1,-2],[-2,-1],[-2,0],[-1,-1],[-1,-1],[-2,1],[-3,-1],[-1,0],[-1,-1],[-4,-4],[-2,-1],[-1,-1],[-1,0],[-1,-1],[-2,-3],[-2,0],[-1,-2],[-1,0],[-2,-2],[-1,-1],[-3,-1],[-1,0],[-1,-1],[0,-1],[-1,0],[-4,-4],[-1,-1],[-1,-1],[0,-1],[-1,0],[0,-1],[-1,-1],[-1,0],[-1,-1],[-4,-4],[0,-1],[-2,-3],[0,-1],[0,-1],[-3,-4],[-1,0],[-1,-1],[0,-1],[-2,-1],[-1,0],[-1,1],[-1,-1],[-2,-1],[0,1],[-1,-1]],[[9995,7954],[1,1],[0,-1],[0,-1],[-1,1],[0,-1],[0,-2],[1,0],[0,1],[0,1],[0,1],[1,0],[-1,-2],[0,-2],[0,-1],[-1,-2],[0,-1],[-1,-2],[0,-2],[0,-1],[-1,-2],[0,-2],[0,-1],[0,-1],[-1,-1],[0,-1],[-1,-1],[-1,2],[0,1],[-1,0],[0,1],[-1,0],[-1,1],[0,1],[-1,1],[0,1],[1,0],[0,1],[0,1],[1,0],[0,1],[0,1],[0,2],[1,1],[0,1],[0,2],[1,0],[0,2],[1,0],[3,2],[1,0]],[[9995,7954],[1,0],[0,-1],[0,1],[-1,0],[0,-1],[0,-2],[1,0],[0,1],[0,1],[0,1],[1,0],[1,0],[0,-1],[0,-2],[0,-2],[0,-1],[0,-3],[0,-1],[0,-3],[0,-1],[0,-1],[-1,-2],[0,-1],[-1,0],[0,-1],[-1,-3],[0,-1],[-1,0],[0,-1],[0,-1],[0,-1],[1,-1],[0,-1],[0,-1],[0,-1],[0,-1],[1,-1],[0,-1],[1,0],[0,-1],[0,-1],[1,-1],[0,-1],[1,-1],[0,-2],[0,-1],[0,-1],[0,-1],[0,-2],[-1,-3],[0,-2],[0,1],[-1,0],[-1,1],[0,-1],[-1,0],[-1,0],[-1,0],[0,-1],[-1,0],[-1,0],[0,-1],[0,1],[0,-1],[0,1],[-1,-1],[-1,0],[-1,0],[-1,0],[0,-1],[-1,0],[-1,0],[-1,0],[0,1],[0,1],[0,1],[0,1],[0,1],[0,1],[0,1],[0,1],[0,2],[0,1],[0,1],[0,1],[0,1],[0,1],[0,2],[0,1],[0,1],[0,1],[0,1],[0,1],[0,1],[0,1],[0,1],[0,1],[0,2],[0,1],[0,1],[0,1],[0,1],[0,1],[0,1],[0,1],[0,1],[0,1],[0,2],[0,1],[0,1],[0,1],[0,1],[0,1],[0,1],[0,1],[0,1],[0,1],[0,1],[0,2],[0,1],[1,0],[1,0],[1,0],[1,0],[0,1],[1,0],[0,-1],[0,-1],[0,-1],[0,-1],[0,-1],[1,0],[0,1],[0,1],[1,0],[1,1],[1,0],[1,1],[1,0]],[[5339,3765],[0,27],[1,0],[0,59],[1,1],[2,1],[1,2],[1,2],[0,2],[1,3],[1,3],[0,2],[1,1],[2,2],[1,0],[2,0],[1,-3],[1,-3],[1,-2],[0,-1],[2,-3],[1,-1],[0,-1],[1,-3],[0,-2],[0,-2],[0,-2],[1,2],[2,3],[3,2],[3,1],[3,-3],[2,-5],[2,-5],[2,-7],[2,-5],[2,-1],[3,5],[1,2],[2,7],[2,5],[0,4],[1,3],[2,1],[1,-2],[2,2],[1,2],[0,4],[-1,5],[-1,5],[-1,6],[1,2],[0,4],[1,2],[1,0],[2,0],[1,-1],[1,-2],[1,1],[1,3],[-1,3],[0,1],[-2,2],[-1,2],[0,4],[3,3],[2,1],[1,-2],[1,-1],[2,2],[1,3],[1,9],[2,3],[2,2],[1,3],[0,4],[0,8],[0,3],[1,4],[1,3],[1,4],[1,1],[2,3],[0,1],[1,-1],[2,-1],[2,0],[1,-2],[0,-8],[1,-9],[1,-4],[0,-1],[1,-2],[2,-2],[2,-2],[1,-1],[3,0],[2,0],[1,0],[1,-2],[1,-2],[1,-1],[0,-1],[1,-1],[1,-1],[2,0],[1,0],[1,2],[1,0],[1,0],[0,-1],[1,-2],[0,-4],[1,-3],[-1,-4],[-1,-5],[-2,-3],[-2,-4],[0,-4],[2,-2],[1,1],[4,3],[4,2],[1,2],[1,4],[1,3],[1,0],[1,1],[1,-1],[1,-1],[0,-1],[0,-1],[1,-3],[0,-7],[0,-4],[1,-5],[0,-4],[1,-2],[0,-2],[1,-76],[-24,-1],[0,-90],[-86,1],[0,64],[-21,0]],[[3972,9148],[1,0],[1,0],[0,1],[0,1],[1,0],[0,1],[1,0],[1,-1],[1,0],[0,1],[0,1],[-1,0],[0,1],[0,1],[1,1],[0,-1],[1,0],[0,-1],[0,-1],[0,-1],[0,-1],[0,-1],[1,0],[0,-1],[0,-1],[0,-1],[-1,0],[0,-1],[0,-1],[0,-1],[-1,0],[1,-1],[0,-1],[0,-1],[0,-1],[1,0],[0,-1],[1,0],[1,0],[0,1],[0,1],[0,1],[0,1],[0,1],[0,1],[0,1],[1,-1],[0,-1],[1,0],[1,0],[0,-1],[1,0],[0,-1],[1,0],[1,0],[1,0],[1,0],[1,0],[0,1],[0,1],[1,0],[0,1],[0,1],[1,0],[0,-1],[0,-1],[1,0],[0,-1],[0,1],[0,1],[0,1],[0,1],[0,1],[0,1],[1,1],[0,1],[0,1],[1,0],[0,1],[0,1],[1,0],[0,1],[0,1],[0,1],[0,1],[0,2],[0,9],[0,10],[0,9],[0,18],[0,9],[0,10],[0,9],[0,8],[0,9],[0,9],[0,9],[0,10],[0,9],[0,28],[0,18],[2,0],[23,0],[2,-1],[22,1],[3,0],[9,0],[13,0],[2,0],[22,0],[24,0],[25,0],[24,-1],[24,1],[0,-93],[0,-1],[-1,0],[0,-1],[-1,-1],[-1,0],[-1,0],[0,1],[1,0],[0,1],[0,1],[0,1],[-1,1],[0,-1],[-1,0],[0,-1],[-1,-1],[0,-1],[0,-1],[0,1],[0,1],[-1,1],[-1,0],[0,-1],[0,-1],[0,-1],[1,0],[0,-1],[0,-1],[0,-1],[0,-1],[-1,0],[0,1],[-1,0],[0,1],[0,1],[0,1],[0,1],[-1,-1],[0,-1],[0,-1],[0,-1],[-1,0],[0,1],[0,1],[0,1],[0,1],[0,1],[-1,-1],[1,0],[0,-1],[0,-1],[-1,-1],[0,1],[-1,0],[0,1],[-1,0],[-1,-1],[0,-1],[0,-1],[0,-1],[0,-1],[0,-1],[0,-1],[1,1],[0,-1],[1,0],[0,-1],[0,-1],[-1,0],[0,-1],[0,-1],[0,-1],[-1,-1],[0,-1],[-1,0],[0,-1],[-1,0],[0,-1],[-1,0],[0,1],[0,1],[1,1],[0,1],[-1,0],[0,1],[0,1],[0,1],[-1,1],[-1,0],[0,-1],[1,0],[0,-1],[0,-1],[-1,0],[-1,0],[0,-1],[0,-1],[0,-1],[0,-1],[0,-1],[0,-1],[0,-1],[0,-1],[0,-1],[0,-1],[0,1],[0,1],[-1,0],[0,1],[0,-1],[0,-1],[0,-1],[-1,0],[-1,-1],[0,-1],[0,-1],[0,-1],[-1,0],[0,-1],[0,1],[-1,0],[0,1],[0,1],[0,1],[0,1],[0,1],[0,1],[-1,0],[0,1],[-1,-1],[-1,0],[0,-1],[1,-1],[0,-1],[-1,-1],[0,-1],[-1,0],[0,-1],[0,-1],[0,-1],[0,-1],[-1,0],[0,-1],[0,1],[-1,0],[-1,0],[0,-1],[0,-1],[1,-1],[0,-1],[-1,0],[0,-1],[0,-1],[0,-1],[0,-1],[-1,0],[0,-1],[1,-249]],[[3978,8951],[0,55],[-5,0],[0,55],[-1,86],[0,1]],[[8318,2193],[1,-10],[2,-4],[1,-4],[1,-3],[0,-3],[-1,-3],[0,-1],[3,-5],[1,-10],[-1,-18],[0,-13],[0,-3],[-2,-6],[0,-3],[1,-5],[2,-3],[0,-7],[-1,-4],[0,-4],[0,-3],[1,-3],[1,-4],[0,-3],[0,-2],[-1,-2],[-1,0],[0,-1],[0,-2],[0,-2],[1,-1],[-2,-8],[0,-3],[-1,-5],[0,-1],[-1,-3],[0,-1],[0,-2],[1,-5],[1,0],[0,1],[1,1],[2,-2],[-2,-6],[-1,-5],[0,-6],[-2,-4],[-2,0],[-1,-7],[0,-2],[-1,0],[-1,-4],[0,-7],[-1,-1],[-1,1],[-1,1],[0,3],[-2,0],[-1,0],[-2,0],[-2,-1],[0,-4],[-1,-2],[0,-1],[0,-6],[-1,-5],[0,-3],[0,-3],[0,-5],[0,-3],[-10,4],[-5,-1],[1,-3],[2,-6],[0,-4],[-1,-3],[2,-9],[-2,-6],[-2,-4],[-1,-1],[0,-2],[-1,-2],[1,-3],[0,-1],[0,-5],[0,-5],[0,-2],[1,-2],[0,-1],[1,-3],[2,-10],[0,-1],[1,2],[2,-2],[2,-2],[1,0],[0,-3],[1,-2],[1,-2],[1,-5],[0,-2],[0,-5],[0,-7],[-1,-2],[-1,2],[0,2],[0,2],[-2,-1],[0,-6],[2,-2],[-1,-3],[0,-4],[1,-1],[2,3],[1,2],[1,3],[1,0],[1,0],[1,-1],[0,-3],[1,0],[1,2],[1,1],[0,-1],[0,-2],[0,-2],[-1,-1],[-2,-1],[-1,-1],[0,-1],[0,-1],[2,-2],[1,-1],[1,-1],[1,0],[1,-2],[1,-2],[0,-3],[-2,-7],[-1,-3],[0,-5],[1,-1],[0,-1],[1,0],[1,2],[2,1],[29,-1],[-2,-29],[-19,0],[-8,1],[-1,0],[-4,2],[-2,0],[-1,1],[0,2],[-2,3],[-2,7],[-2,7],[-1,1],[-4,4],[-1,2],[-1,2],[-1,5],[0,2],[-1,3],[-1,0],[0,1],[-1,0],[-1,0],[-1,-2],[-1,-4],[-2,-4],[-1,0],[-2,0],[-1,0],[-1,1],[-1,1],[0,1],[-1,0],[-3,7],[-1,2],[-1,2],[0,2],[-2,0],[-2,1],[0,1],[-1,3],[0,1],[0,2],[0,2],[-1,5],[0,1],[0,4],[1,1],[0,2],[0,1],[1,0],[0,1],[0,1],[-1,0],[-1,1],[0,1],[0,1],[0,3],[0,1],[-1,0],[-1,1],[0,1],[0,1],[1,1],[0,2],[1,2],[0,-1],[0,-1],[1,0],[0,-1],[1,1],[0,1],[0,2],[-1,0],[0,-1],[-1,1],[0,1],[0,2],[1,2],[0,2],[-1,1],[0,1],[0,1],[1,0],[0,1],[0,1],[-1,-1],[0,1],[0,3],[-1,1],[-1,4],[0,1],[-1,1],[0,1],[0,2],[0,1],[-1,1],[-1,1],[-1,0],[0,1],[1,1],[0,1],[0,1],[0,2],[0,1],[-1,1],[0,1],[-1,1],[0,1],[0,1],[0,1],[0,1],[0,1],[0,1],[1,1],[0,1],[1,0],[0,1],[-1,2],[0,1],[1,0],[0,1],[0,1],[0,1],[0,1],[0,1],[1,0],[1,0],[0,1],[0,1],[-1,1],[0,1],[0,1],[1,0],[0,-1],[0,-1],[1,1],[0,1],[0,1],[0,1],[0,1],[1,0],[0,-1],[1,0],[-1,1],[0,1],[0,1],[0,1],[0,1],[1,1],[0,1],[0,1],[0,1],[0,1],[0,1],[-1,2],[0,1],[1,1],[0,2],[0,2],[0,1],[-1,1],[0,-1],[-1,0],[-1,1],[1,1],[0,1],[0,1],[0,1],[0,1],[0,2],[0,1],[0,1],[0,1],[0,1],[-1,0],[0,-1],[0,1],[0,1],[0,1],[0,1],[1,2],[0,1],[0,1],[0,1],[0,1],[-1,0],[0,1],[0,1],[-1,1],[0,3],[0,1],[-1,0],[0,-1],[0,-1],[0,-1],[0,-1],[-1,0],[0,-1],[0,-1],[-1,-1],[0,1],[0,-1],[-1,0],[0,1],[1,0],[0,1],[0,1],[0,1],[0,1],[0,1],[0,-1],[-1,0],[0,1],[0,1],[0,1],[0,1],[0,1],[-1,0],[0,1],[0,1],[0,1],[-1,0],[0,1],[-1,0],[0,1],[1,0],[0,1],[0,2],[0,1],[-1,1],[0,1],[0,1],[0,1],[-1,1],[0,1],[0,3],[0,1],[0,2],[0,1],[0,1],[0,2],[-1,2],[0,1],[-1,2],[0,2],[-1,3],[-2,5],[0,2],[0,1],[0,1],[0,1],[0,1],[-1,4],[0,1],[1,1],[1,1],[0,1],[0,1],[0,1],[0,1],[-1,0],[0,-1],[0,1],[0,1],[0,1],[0,1],[0,1],[0,-1],[1,-1],[0,-1],[0,3],[0,1],[1,0],[0,-1],[1,0],[0,1],[-1,0],[0,1],[0,1],[0,1],[1,0],[0,1],[1,1],[0,1],[-1,0],[0,1],[0,-1],[-1,0],[0,1],[-1,1],[0,1],[-1,2],[-1,2],[0,2],[-1,1],[0,1],[-1,1],[0,1],[0,1],[-1,1],[0,1],[0,2],[-1,0],[0,1],[-1,3],[0,1],[0,1],[0,1],[-1,0],[0,1],[0,1],[0,1],[0,1],[0,1],[1,0],[0,1],[0,1],[0,1],[0,1],[-1,0],[0,-1],[-1,0],[0,1],[0,1],[0,1],[0,-1],[-1,-1],[-1,0],[0,1],[-1,1],[0,1],[-1,2],[-1,1],[0,1],[-1,0],[0,1],[0,1],[0,1],[-1,0],[0,1],[-1,1],[1,0],[0,1],[1,1],[0,2],[-1,1],[0,1],[-1,0],[0,1],[0,1],[1,1],[0,1],[0,1],[-1,1]],[[7243,6678],[0,-4],[0,4],[-1,0],[0,10],[1,0],[0,1],[1,0],[0,-2],[1,0],[1,0],[0,1],[1,0],[1,0],[0,1],[0,1],[0,1],[1,0],[0,1],[0,1],[1,0],[0,-1],[0,-1],[0,-1],[0,-1],[0,-1],[-1,-1],[1,0],[0,-5],[0,-4],[4,0],[0,-1],[-5,0],[0,-7],[1,0],[3,1],[0,-1],[0,-1],[-5,-1],[0,-4],[0,-1],[-1,-4],[1,0],[0,-3],[-2,3],[-1,0],[0,4],[1,0],[0,1],[2,0],[0,4],[-4,-1],[-3,1],[0,2],[1,0],[0,-1],[1,0],[1,0],[0,4],[1,0],[0,5],[-2,0]],[[7682,4673],[-6,-4],[-5,2],[-32,-1],[-5,4],[-5,13],[-4,10],[-5,12],[-4,19],[-2,22],[0,17],[2,1],[2,1],[1,-3],[3,-1],[3,3],[2,0],[3,2],[4,3],[3,8],[2,5],[3,4],[2,0],[3,2],[1,8],[-1,10],[1,3],[1,7],[2,-2],[1,-2],[3,6],[1,9],[2,-2],[3,-1],[4,4],[1,1],[1,6],[-1,9],[-1,8],[-2,9],[-1,6],[-3,2],[-2,2],[-4,0],[0,6],[1,8],[2,8],[1,0],[2,-2],[2,2],[3,2],[5,2],[5,3],[6,2],[6,-3],[6,14],[4,16],[4,11],[7,7],[-3,17],[5,12],[-3,18],[-9,8],[-5,14],[-3,18],[5,18],[0,25],[5,0],[5,22],[7,15],[9,8],[5,9],[9,-6],[8,0],[7,8],[4,-18],[4,-16],[5,-11],[6,-8],[7,-6],[5,10],[-7,26],[2,16],[5,6],[5,14],[5,7],[3,-13],[5,-5],[6,-7],[8,11],[8,19],[12,11],[5,19],[5,-15],[5,-5],[7,-4],[2,-17],[0,-19],[-2,-15],[0,-21],[0,-18],[5,-11],[6,-1],[3,0],[5,-13],[6,-7],[6,-13],[8,-5],[3,11],[8,12],[8,23],[11,11],[12,0],[4,-3],[4,-11],[5,-5],[10,11],[5,-14],[4,-14],[-4,-5],[-7,-11],[-6,-10],[-6,-8],[-7,-3],[-2,-13],[-1,-16],[1,-18],[-5,-11],[-4,-13],[-6,-2],[-7,-11],[-4,-10],[-2,-14],[1,-19],[-4,-21],[-6,-10],[-8,-11],[-8,0],[-10,-1],[-8,-8],[-3,-17],[-5,-18],[-2,-26],[-6,-3],[-11,-6],[-13,-11],[-11,-8],[-10,-14],[-11,-6],[-8,-2],[-11,-6],[-11,-10],[-10,-9],[-6,-11],[-5,-16],[-7,-1],[-12,3],[-9,-2],[-7,2],[-9,-2],[-8,0],[-7,2]],[[7660,4897],[1,4],[5,9],[3,0],[1,0],[1,6],[1,1],[5,-1],[2,-4],[1,1],[0,-1],[4,0],[1,-1],[1,-1],[1,0],[3,7],[2,5],[0,3],[0,4],[1,4],[1,4],[0,4],[0,3],[1,4],[1,0],[1,-2],[4,6],[2,0],[1,2],[0,4],[1,1]],[[7704,4728],[-17,25],[0,14],[-2,7],[-2,1],[0,-2],[-1,0],[-1,6],[3,6],[0,3],[-1,4],[0,5],[-1,3],[-3,-1],[0,1],[0,3],[0,3],[-2,3],[-1,-2],[-3,3],[0,6],[-2,3],[-1,3],[0,2],[1,1],[0,4],[-3,5],[0,-2],[-1,0],[-2,0],[0,6],[2,4],[-2,9],[0,2],[0,2],[-1,1],[-2,4],[0,3],[-1,7],[0,6],[1,6],[0,1],[-1,5],[-1,3],[0,6]],[[7779,5074],[2,5],[2,3],[1,1],[1,5],[0,6],[-1,2],[0,4],[2,7],[2,2],[1,1],[1,-2],[1,-1],[2,-1],[2,2],[0,2],[0,4],[0,2],[1,1],[1,3],[1,1],[1,2],[2,3],[1,1],[2,-7],[0,-3],[1,0],[1,0],[1,-2],[0,-3],[0,-1],[2,2],[1,1],[1,-2],[0,-2],[0,-4],[1,-3],[2,-6],[-1,-3],[0,-3],[1,-8],[0,-1],[1,-1],[0,-4],[-1,-3],[0,-1],[2,-3],[1,-3],[1,1],[1,1],[0,1],[1,-1],[1,-4],[0,-3],[1,-2],[1,0],[0,2],[1,0],[1,-5],[1,-4],[1,-1],[2,-1],[2,2],[0,-3],[1,-2],[0,-1],[2,1],[0,-2],[2,-5],[3,-3],[2,-2],[1,-1],[0,-5],[-2,0],[0,-1],[-1,-5],[-1,2],[-1,-2],[0,-2],[0,-2],[1,-1],[0,-3],[-1,-4],[0,-1],[2,-2],[1,-2],[1,-1],[2,-7],[0,-2],[0,-4],[2,2],[1,-3],[3,-3],[0,-5],[-1,-5],[-1,-1],[0,-2],[1,-2],[1,-3],[0,-5],[-3,-3],[0,-3],[0,-4],[1,-4],[0,-3],[-2,-6],[0,-2],[0,-3],[1,0]],[[7858,4925],[1,-2],[1,-3],[1,0],[1,1],[3,5],[3,6],[2,2],[1,1],[1,1],[1,7],[0,4],[-4,5],[-1,3],[1,2],[1,2],[1,2],[2,1],[1,2],[1,10],[-2,5],[0,4],[-1,2],[1,2],[0,2],[0,1],[-1,4],[-1,4],[0,6],[1,2],[4,17],[0,1],[-1,3],[1,2],[0,2],[1,1],[2,3],[0,2],[1,4],[1,4],[2,3],[1,0],[1,-3],[1,-2],[0,-7],[1,-3],[2,5],[2,1],[2,6],[2,0],[1,4],[1,3],[3,1],[2,1],[1,4],[2,2],[0,2],[1,4],[0,1],[1,2],[1,1],[1,1],[0,6],[1,4],[1,1],[1,0],[2,3],[1,2],[3,4],[1,1],[1,2],[2,-1],[2,-2],[1,-1],[2,0],[2,1],[3,3],[1,0],[1,-2],[1,0],[3,4],[2,-5],[2,-3],[2,-1],[0,-1],[1,-4],[-1,-2],[2,-5],[2,-7],[2,0],[1,0],[0,1],[3,6],[1,3],[3,3],[1,-1],[2,-5],[1,-2],[1,-2],[2,-2],[0,-3],[1,-8],[1,-2],[3,-3],[2,-5],[-3,-4],[0,-1],[-1,-1],[-2,-2],[0,-1],[0,-1],[-1,-2],[-2,-2],[-2,-3],[-1,-4],[-2,-5],[-2,-1],[-2,-1],[-1,-4],[-1,-1],[-1,-1],[-1,-2],[-1,-2],[-1,0],[-2,-1],[-1,-1],[-2,-4],[-1,-2],[-1,0],[-1,-2],[-1,-2],[0,-1],[0,-2],[1,-4],[0,-3],[0,-4],[-1,-1],[1,-5],[0,-2],[1,0],[0,-1],[0,-2],[0,-1],[-1,0],[-1,-1],[0,-4],[1,-3],[0,-3],[0,-3],[0,-3],[0,-2],[-1,-1],[0,-1],[-1,1],[0,1],[-1,0],[-1,-1],[-1,-1],[0,-8],[0,-2],[-1,-1],[0,1],[-1,0],[-1,1],[-1,-3],[0,-1],[-1,-3],[-1,-1],[-1,-1],[0,-3],[-1,0],[-1,0],[0,-1],[-1,-1],[0,1],[0,1],[-1,1],[0,-1],[-3,-2],[0,1],[-1,0],[-1,-1],[0,-1],[0,2],[-1,-1],[0,-1],[0,-2],[0,-2],[0,-1],[0,-1],[-1,-1],[0,-2],[-1,-1],[0,-1],[-1,-2],[-1,0],[-1,1],[-1,-2],[0,-2],[-1,1],[0,-1],[-1,0],[0,-1],[0,-2]],[[651,3219],[1,0],[0,2]],[[652,3221],[1,0],[0,1],[1,0],[0,-1],[1,0],[0,-2]],[[655,3219],[0,-1],[-1,0]],[[654,3218],[0,-2]],[[654,3216],[0,-3],[1,0],[1,-1],[0,1],[1,-1],[0,1],[0,1],[1,0],[-1,0],[0,-1],[0,-1],[1,1],[0,-1],[0,-1],[1,0],[0,-1],[2,0],[0,2],[5,0],[0,2],[6,0],[0,5],[2,0],[0,-1],[1,0],[-1,-9],[3,0],[0,2],[7,0],[0,-9],[-3,0],[0,-9],[-2,0],[0,-1],[0,-2],[0,-1],[0,-1],[0,-1],[0,-1],[0,-1],[0,1],[0,-12],[-5,0],[-1,0],[-9,-1],[1,-2],[0,-1],[-1,-1],[0,-1],[0,-1],[0,-3],[-2,0],[-1,0],[-2,0],[0,-3],[-1,0],[-1,-3],[1,-1],[1,-1],[0,-1],[0,-3],[1,0],[0,-1],[0,-1],[0,-1],[0,-1],[0,-1],[0,-1],[0,-1],[0,-2],[0,-1],[0,-1],[0,-1],[0,-1],[1,-1],[-1,0],[0,-1],[0,-1],[1,0],[0,-1],[0,-1],[0,-1],[0,-1],[1,-1],[0,-1],[0,-1],[0,-1],[0,-1],[0,-1],[0,-1],[0,-1],[1,0],[0,1],[1,1],[1,1],[1,1],[0,1],[0,1],[1,0],[0,1],[0,1],[1,0],[0,-1],[1,0],[0,1],[1,3],[0,1],[0,-1],[1,-1],[1,-1],[0,1],[1,0],[0,-1],[0,-1],[1,0],[1,0],[0,1],[1,0],[0,-1],[0,-1],[0,-1],[1,0],[0,-2],[0,-1],[0,-1],[1,-3],[0,-3],[1,-1],[0,-1],[0,-1],[0,-2],[1,-1],[0,-1],[0,-1],[0,-1],[1,-1],[0,-1],[1,1],[0,1],[-1,0],[0,1],[1,0],[1,1],[1,0],[1,1],[0,1],[0,2],[0,1],[0,1],[1,0],[1,0],[0,2],[-1,0],[0,1],[0,2],[0,1],[0,1],[0,1],[1,0],[0,1],[1,0],[0,-1],[1,0],[0,-1],[1,0],[1,1],[0,1],[1,1],[1,0],[0,-1],[1,0],[1,0],[0,-1],[0,-1],[0,-1],[1,0],[0,-1],[0,-1],[0,-1],[-1,0],[0,-1],[0,-1],[0,-1],[0,-1],[0,-1],[1,0],[0,-1],[0,-1],[0,1],[0,-1],[0,-1],[1,0],[0,-1],[0,-1],[1,0],[0,1],[0,1],[1,0],[0,-1],[0,-1],[0,1],[0,-1],[0,-1],[0,-1],[0,-1],[0,-1],[-1,0],[0,-1],[0,-1],[0,-1],[-1,0],[0,-1],[0,-1],[0,-1],[0,-1],[0,-1],[0,-1],[0,-1],[0,-1],[0,-1],[1,0],[1,0],[1,0],[1,0],[0,-1],[0,-1],[0,-1],[-1,0],[0,-1],[0,-1],[0,-3],[0,-1],[0,-2],[0,-2],[0,-2],[0,-1],[0,-1],[0,-1],[0,-1],[0,-2],[-1,0],[0,-1],[0,-1],[-1,0],[-1,0],[-1,0],[-1,0],[-1,0],[0,-1],[0,-2],[0,-1],[0,-1],[0,-1],[0,-1],[0,-1],[0,-1],[0,-1],[0,-1],[0,-1],[0,-1],[0,-1],[0,-1],[0,-1],[0,-1],[0,-1],[0,1],[0,-1],[0,-1],[0,-1],[0,-1],[0,-1],[0,-1],[0,-1],[0,-1],[0,-1],[0,-1],[0,-2],[0,-1],[0,-1],[-2,0],[0,1],[-1,0],[0,-1],[0,1],[-1,0],[-1,0],[0,1],[0,-1],[-2,0],[0,1],[0,-1],[0,1],[0,-1],[-1,0],[-2,0],[0,-1],[0,-1],[0,-2],[0,-11],[0,-1],[-1,0],[-1,0],[-1,0],[0,-1],[0,-1],[0,-1],[0,-1],[0,-1],[0,-1],[0,-1],[0,-1],[0,-1],[0,-1],[0,-1],[0,-1],[0,-1],[0,-1],[0,-1],[0,-1],[0,-1],[0,-1],[0,-1],[0,-1],[0,-1],[0,-1],[0,-1],[0,-1],[0,-1],[0,-1],[0,-1],[0,-1],[0,-1],[1,0],[0,1],[0,1],[0,1],[0,1],[0,2],[0,1],[1,0],[0,-1],[1,0],[1,0],[0,-1],[0,-2],[1,0],[-1,0]],[[685,3001],[0,-1],[1,0],[0,-1]],[[686,2999],[0,-1],[0,-3],[0,-1],[0,-3],[0,-2],[-1,0],[-1,0],[-1,0],[-1,0],[-1,0],[0,-1],[0,-1],[0,-1],[0,-1],[-1,0],[-1,0],[-1,0],[-1,0],[0,1],[-1,0],[0,-1],[0,1],[0,-1],[-1,0],[0,-1],[0,-1],[0,-1],[0,-1],[0,-1],[0,-1],[0,-1],[0,-1],[0,-3],[0,-2],[0,-1],[0,-1],[0,-1],[0,-1],[0,-1],[0,-1],[0,-1],[0,-1],[0,-2],[0,-2],[0,-1],[0,-1],[0,-1],[0,-1],[0,-1],[0,-1],[1,-1],[0,-1],[0,-1],[0,-1],[0,-1],[0,-1],[0,-1],[-1,-1],[-1,-1],[0,-3],[1,0],[0,-1],[0,-2],[0,-2],[-3,0],[0,-3],[0,-2],[0,-1],[0,-1],[0,-2],[0,-1],[0,-2],[0,-1],[0,-1],[0,-7],[0,-6],[0,-1],[0,-3],[1,0],[1,0],[1,0],[0,1],[4,0],[0,4],[1,0],[1,0],[0,-1],[-1,-3],[1,1],[4,0],[1,-5],[0,2],[0,1],[1,2],[0,3],[0,1],[0,1],[0,2],[-1,8],[1,3],[0,-3],[0,-2],[1,-5],[0,-6],[-1,-7],[0,-1],[0,-1]],[[687,2901],[0,-1]],[[687,2900],[1,-3],[-5,-12],[1,-3],[-1,-2],[-1,0],[4,-26],[-1,0],[-3,-4],[-1,0],[-2,-3],[-1,0],[0,1],[-1,0],[0,1],[-1,1],[0,-1],[0,1],[0,1],[-1,0],[0,-1],[0,-1],[-1,0],[0,-1],[-1,0],[0,1],[0,1],[-1,0],[0,1],[-1,0],[0,1],[-1,0],[0,1],[-1,1],[-1,0],[0,-1],[0,1],[0,-1],[0,1],[0,1],[0,-1],[0,1],[0,1],[-1,0],[0,1],[-1,0],[0,1],[-1,0],[0,1],[0,2],[1,1],[0,1],[1,0],[0,1],[1,0],[0,1],[0,1],[0,1],[0,1],[0,1],[0,1],[0,1],[0,1],[0,2],[1,0],[0,1],[1,0],[0,-1],[0,1],[0,1],[0,2],[0,1],[0,1],[0,1],[2,0],[-1,2],[-1,0],[0,1],[-1,1],[1,1],[0,1],[0,1],[0,1],[0,1],[0,1],[0,1],[0,3],[0,1],[0,1],[0,1],[0,1],[0,1],[0,1],[0,1],[0,1],[0,1],[0,1],[0,1],[0,1],[0,1],[0,1],[0,1],[0,1],[0,1],[0,1],[0,1],[0,1],[0,1],[0,2],[0,1],[0,1],[0,1],[0,1],[0,1],[0,1],[0,1],[0,14],[0,1],[0,1],[0,3],[0,1],[0,2],[0,2],[1,0],[1,0],[0,3],[1,0],[0,-2],[-1,0],[0,-1],[1,0],[1,0],[0,1],[0,7],[0,3],[-1,7],[0,7],[0,3],[0,4],[0,6],[0,21],[-1,0],[0,-6],[-1,0],[0,-2],[0,-3],[-1,0],[0,-2],[-1,0],[0,5],[-1,0],[0,2],[0,1],[0,1],[0,1],[0,1],[0,1],[0,1],[0,1],[0,1],[0,1],[0,1],[0,1]],[[668,3013],[0,1]],[[668,3014],[0,1],[0,1],[-1,0],[0,-1],[0,1],[-1,0],[0,-1],[0,-1],[0,-1],[-1,0],[0,1],[0,1],[0,1],[0,1],[0,1],[0,1],[0,1],[0,1],[0,1],[-1,0],[-1,0],[-1,0],[-1,0],[-1,0],[-1,0],[-1,0],[-1,0],[0,-1],[0,-1],[0,-1],[0,-1],[0,-1],[0,-1],[0,-1],[0,-1],[0,-1],[0,-2],[0,-1],[-1,0],[0,-1],[0,-1],[0,-1],[0,-1],[0,-1],[0,-1],[1,0],[0,-1],[0,-1],[0,-1],[0,-1],[0,-1],[0,-4],[0,-3],[0,-2],[1,0],[0,-1],[-1,0],[-1,0],[0,1],[-1,0],[-1,0],[-1,0],[-1,0],[-1,1],[-1,0],[-1,0],[-1,0],[-2,0],[-1,-1],[0,-2],[1,0],[0,-1],[0,-1],[0,-1],[0,-2],[1,0],[0,-1],[0,-1],[-1,0],[-1,0],[-1,0],[-13,0],[0,2],[-1,6],[-1,2],[-1,4],[-1,4],[-1,5],[0,2],[-2,4],[-1,3],[8,12],[2,4],[1,1],[1,0],[-1,1],[1,1],[0,1],[1,0],[0,1],[0,1],[1,0],[0,1],[1,0],[0,1],[0,1],[1,0],[0,1],[1,1],[1,2],[1,1],[0,1],[0,1],[0,1],[0,1],[-1,1],[0,2],[0,1],[0,1],[-1,0],[0,1],[0,1],[-1,0],[0,1],[-1,1],[0,1],[0,1],[-1,0],[0,1],[0,1],[-1,2],[0,1],[-1,0],[0,-1],[0,-1],[-1,-1],[0,1],[0,1],[-1,0],[0,1],[0,1],[-1,1],[0,1],[0,-1],[0,-1],[-1,0]],[[631,3064],[0,-1]],[[631,3063],[-1,-2],[0,-1],[0,-1],[0,1],[0,-1],[-1,0],[0,-1],[0,-1],[0,-1],[0,-1],[0,-1],[0,-1],[-1,0],[0,-1],[0,-1],[0,-1],[-1,0],[0,-2],[0,-1],[-4,-13],[-3,-11],[-1,3],[-1,0],[-1,0],[0,1],[0,33],[0,2],[0,1],[0,1],[-1,14],[-5,3],[7,35],[-10,11],[-1,1],[0,-1],[-1,0],[-1,-1],[0,1],[-1,1],[0,1],[-1,3],[0,1],[-1,0],[0,1],[0,1],[0,1],[-1,0],[0,1],[0,1],[-1,0],[-1,0],[0,3],[-1,0],[1,0],[0,1],[0,1],[0,1],[-1,0],[1,1],[-1,0],[1,0],[-2,0],[0,5],[0,4],[0,3],[0,7],[0,2],[1,0],[0,2],[2,0],[0,2],[-1,0],[-1,0],[0,1],[0,2],[0,1],[0,1],[1,1],[0,1],[1,0],[1,7],[1,0],[2,-1],[0,1],[0,6],[0,10],[0,1],[0,2],[0,1],[0,2],[1,0],[0,1],[1,0],[0,1],[3,1],[1,0],[1,-2],[1,1],[0,1],[0,1],[0,1],[0,1],[0,1],[0,1],[0,1],[0,3],[0,4],[1,3],[1,0],[2,-3],[0,-1],[1,-1],[1,1],[0,1],[1,0],[1,-1],[1,0],[0,1],[2,0],[-1,1],[0,1],[0,1],[0,2],[0,2],[-1,2],[1,2],[-1,1],[3,-2],[6,14],[2,-4],[6,0],[2,0],[3,0],[4,0],[0,-1],[0,1],[1,0],[-1,-1],[0,-1],[0,-1],[1,0],[0,-1],[0,1],[1,0],[0,1],[0,2],[1,0],[0,-5],[1,-1],[0,-1],[1,0],[0,-1],[-1,0],[0,-1],[0,-1],[0,-3],[0,-1],[-1,0],[0,-2],[0,-3],[1,0],[0,-2],[0,-2],[-2,0],[1,-1],[-1,0],[0,-1],[0,-1],[1,-2],[1,0],[0,2],[0,1],[0,1],[0,1]],[[641,3030],[1,-1],[0,-1],[1,1],[0,1],[1,1],[0,-1],[0,-1],[1,0],[0,-1],[0,-1],[0,1],[0,1],[0,1],[0,2],[1,0],[1,0],[1,1],[0,1],[0,1],[0,1],[1,-1],[0,-1],[0,1],[1,0],[0,-1],[0,-1],[0,1],[0,1],[1,1],[0,-1],[0,-1],[0,-1],[0,-1],[0,-1],[-1,0],[0,-1],[0,-1],[0,-1],[0,-1],[0,-1],[1,0],[0,-1],[0,1],[1,0],[0,-1],[0,-1],[0,-1],[0,-1],[1,-1],[0,-1],[1,-1],[0,1],[0,-1],[1,0],[1,0],[1,1],[0,1],[0,2],[1,0],[1,0],[1,0],[1,0],[0,1],[0,1],[0,1],[0,1],[1,0],[1,0],[1,0],[0,1],[0,2],[0,1],[0,1],[1,0],[0,1],[0,1],[0,1],[0,1],[0,1],[0,1],[0,1],[-1,0],[0,-1],[0,-1],[-1,0],[-1,0],[-1,0],[0,-1],[0,-1],[-1,0],[0,-1],[0,-1],[0,-1],[0,1],[0,1],[0,1],[0,3],[0,1],[0,1],[-1,-1],[0,-1],[-1,-1],[0,1],[0,6],[-1,0],[0,-2],[0,-1],[0,1],[0,1],[0,1],[0,1],[0,1],[0,-1],[-1,1],[0,-1],[0,1],[-1,1],[1,0],[0,1],[0,1],[0,1],[0,1],[0,1],[0,1],[1,0],[0,1],[0,1],[0,1],[1,0],[-2,-1],[0,-1],[-1,0],[0,-1],[-1,-1],[-1,0],[0,-1],[0,-1],[-1,0],[0,-1],[0,-1],[0,-1],[-1,0],[0,-1],[0,-1],[-1,0],[0,1],[0,-1],[-1,0],[0,-1],[0,-1],[-1,0],[0,-1],[0,-1],[-1,0],[0,-1],[0,-1],[0,1],[0,-1],[1,0],[0,-1],[-1,0],[0,-1],[0,-1],[0,-1],[1,-1],[-1,0],[0,-1],[-1,0],[0,1],[0,1],[-1,0],[0,-1],[0,-1],[-1,0],[0,-1],[0,-1],[-1,0],[0,-1],[-1,1],[0,-1],[-1,0]],[[657,3073],[0,1]],[[657,3074],[0,1],[0,1],[0,1],[-1,0],[0,1],[-1,0],[0,1],[-1,0],[-1,0],[0,1],[0,1],[0,1],[1,0],[1,0],[1,0],[0,1],[0,1],[0,-1],[0,1],[0,2],[1,0],[0,-2],[0,1],[0,1],[-1,0],[0,1],[0,3],[1,0],[0,1],[0,-2],[0,-1],[0,1],[1,0],[0,1],[1,0],[0,-1],[1,0],[1,0],[0,1],[1,0],[1,0],[0,1],[0,1],[0,1],[-1,0],[-1,0],[-1,0],[-1,0],[0,2],[-1,0],[0,1],[0,-1],[-1,0],[0,-1],[-1,0],[0,-1],[0,-1],[-1,0],[0,1],[-1,0],[0,-1],[0,-1],[-1,0],[-1,0],[0,2],[0,1],[0,1],[1,1],[0,1],[0,2],[0,1],[0,1],[0,1],[0,1],[0,2],[-1,0],[0,-1],[-1,0],[1,-2],[-1,0],[0,-1],[0,-3],[0,-2],[0,-2],[0,-1],[-1,1],[0,1],[0,1],[0,1],[0,1],[0,-1],[-1,0],[1,0],[0,-1],[-1,0],[1,0],[-1,0],[0,-1],[1,0],[-1,0],[0,-1],[0,-1],[0,-1],[0,1],[-1,0],[-1,0],[0,-2],[-1,0],[0,-1],[0,-2],[0,-1],[0,-1],[1,0],[0,-1],[0,-1],[-1,0],[1,0],[0,-1],[0,-1],[0,-1],[0,-1],[1,-1],[0,-1],[0,-1],[0,-3],[1,0],[-1,0],[1,-2],[0,-1],[1,-2],[0,-1],[0,-1],[0,1],[0,1],[0,1],[1,0],[1,0],[1,0],[1,0],[1,0],[0,1],[0,1],[0,1],[0,1],[1,0],[0,-2],[0,-1],[0,1],[1,1]],[[640,3213],[0,-1],[1,0],[0,-1],[0,-1],[0,-1],[1,-1],[0,-1],[0,-1],[1,1],[0,1],[0,1],[1,0],[0,1],[0,-1],[1,0],[0,1],[0,1],[1,1],[0,1],[0,1],[1,0],[0,1],[1,2],[0,1],[0,1],[0,2],[-1,-1],[0,-1],[0,2],[-1,1],[0,1],[-1,1],[0,1],[0,1],[-1,-1],[0,-1],[0,-1],[-1,-1],[0,-1],[0,-1],[-1,0],[0,-1],[0,-1],[-1,0],[0,-1],[0,-1],[0,-1],[-1,-1],[0,-1]],[[643,3023],[-1,1]],[[642,3024],[-1,0],[0,1]],[[641,3025],[-1,0]],[[640,3025],[0,0]],[[640,3025],[0,-1],[-1,-1],[0,-1],[-1,0],[1,-1],[0,-1],[0,-1],[0,-1],[1,-1],[0,-1],[0,-1],[0,-2],[1,0],[0,-1],[0,-1],[3,7],[1,0],[0,1],[-1,0],[0,1],[0,1],[-1,0],[0,1],[0,1]],[[637,3075],[0,-1],[0,-1],[0,-1],[1,0],[0,-1],[0,-1],[0,-1],[1,-1],[1,-4],[0,1],[1,-1],[0,1],[1,0],[-1,2],[0,1],[1,1],[0,1],[-1,2],[0,1],[0,1],[-1,0],[0,1],[0,1],[-1,-1],[1,-2],[0,-1],[-1,-2],[0,1],[0,1],[0,2],[-1,0],[0,1],[0,1],[0,1],[-1,-1],[0,-1]],[[670,2871],[0,-2],[2,0],[0,3],[0,1],[0,-1],[-1,0],[0,-1],[0,-1],[0,1],[-1,0]],[[672,2945],[0,-7],[0,7]],[[651,3219],[1,0],[0,2]],[[655,3219],[0,-1],[-1,0]],[[654,3218],[0,-1],[0,-1]],[[685,3001],[0,-1],[1,0],[0,-1]],[[687,2901],[0,-1]],[[668,3013],[0,1]],[[631,3064],[0,-1]],[[657,3073],[0,1]],[[643,3023],[-1,1]],[[641,3025],[-1,0]],[[640,3025],[0,0]],[[5773,9930],[0,1],[0,1],[0,1],[0,1],[0,1],[0,1],[0,2],[0,1],[0,1],[0,1],[0,1],[0,1],[0,1],[0,1],[0,1],[0,1],[0,1],[0,3],[0,1],[1,0],[1,0],[0,1],[0,2],[0,1],[0,1],[0,2],[0,1],[0,1],[0,2],[0,1],[0,1],[0,1],[0,1],[0,1],[0,2],[0,1],[0,1],[0,1],[0,1],[0,1],[0,1],[0,1],[0,1],[0,3],[0,1],[0,1],[0,1],[0,1],[0,1],[0,2],[0,1],[0,1],[0,1],[0,1],[-1,0],[0,1],[0,1],[1,-1],[0,1],[0,2],[0,1],[0,1],[0,1],[1,0],[1,0],[1,0],[1,0],[1,0],[1,0],[1,0],[1,0],[0,-3],[0,-2],[0,-2],[-1,-3],[1,0],[1,0],[1,0],[1,0],[1,0],[1,0],[1,0],[1,0],[1,0],[1,0],[1,0],[1,0],[0,-1],[0,-2],[0,-1],[0,-1],[0,-1],[0,-1],[0,-1],[0,-1],[0,-1],[0,-2],[0,-1],[0,-1],[1,0],[1,0],[0,-5],[1,0],[1,0],[0,1],[0,-1],[0,-3],[0,-1],[0,-2],[0,-3],[0,-1],[0,-1],[0,-4],[0,-1],[0,-2],[0,-1],[0,-1],[0,-1],[0,-1],[0,-1],[0,-1],[0,-2],[0,-1],[0,-1],[0,-1],[0,-1],[0,-1],[0,-1],[0,-1],[0,-1],[1,-1],[0,-1],[0,-2],[0,-2],[0,-3],[0,-2],[0,-2],[0,-2],[0,-3],[0,-2],[0,-3],[0,-2],[0,-1],[0,-1],[1,0],[0,-1],[0,-1],[1,0],[-1,0],[-1,0],[-1,0],[0,-1],[0,-1],[0,-1],[0,-1],[0,-1],[0,-1],[-1,0],[0,-2],[-1,1],[0,1],[-1,0],[0,-1],[0,1],[0,1],[-2,0],[0,-1],[-1,0],[1,0],[0,1],[-2,0],[-1,0],[0,-1],[0,1],[-2,0],[0,-1],[0,-1],[0,-1],[1,0],[0,-1],[-1,0],[-1,0],[-1,0],[-1,0],[-1,0],[-1,0],[0,-1],[-1,1],[-1,-1],[-1,0],[0,1],[-1,0],[-1,0],[-1,0],[-1,0],[-1,0],[0,1],[0,1],[0,1],[0,1],[0,2],[0,1],[0,1],[0,1],[-1,0],[-1,0],[0,1],[0,1],[0,1],[0,2],[0,1],[0,1],[0,1],[0,1],[0,1],[0,1],[0,1],[0,2],[0,1],[0,1],[0,1],[0,1],[0,1],[0,3],[0,1]],[[9480,6786],[-2,0],[-5,2],[0,2],[0,2],[0,6],[5,2],[0,-3],[1,-2],[1,-5],[1,-1],[-1,-3]],[[9498,6753],[-1,-1],[-1,1],[-1,0],[0,-1],[-1,0],[0,1],[0,1],[0,1],[0,1],[-1,2],[-1,-1],[-1,0],[0,4],[-1,9],[0,9],[1,9],[0,1],[1,1],[1,0],[2,-2],[2,3],[1,3],[2,1],[0,-1],[2,-7],[0,1],[1,-2],[-1,-1],[0,-2],[1,0],[1,0],[0,-1],[-1,0],[-2,-5],[-1,1],[-1,-3],[1,-1],[0,-2],[0,-3],[0,-2],[-1,-1],[-1,-1],[-1,-1],[0,-4],[1,1],[1,-3],[-1,-1],[0,-4]],[[3985,8706],[-57,0],[-16,0],[-10,0],[-14,0],[-4,0],[-24,0],[-20,0],[-42,0],[-1,300],[0,72],[0,10],[1,1],[1,1],[0,1],[0,1],[1,0],[0,-1],[1,0],[0,1],[1,0],[0,1],[0,1],[0,1],[0,1],[1,0],[0,-1],[1,0],[1,0],[0,-1],[1,-1],[1,0],[0,1],[0,1],[1,0],[1,0],[1,0],[1,1],[0,1],[0,1],[1,0],[0,1],[0,1],[0,1],[0,1],[-1,0],[0,1],[0,1],[0,1],[0,1],[1,0],[0,1],[0,1],[0,1],[1,0],[0,1],[0,1],[1,1],[0,1],[-1,0],[0,1],[0,1],[0,1],[0,1],[0,1],[1,0],[0,1],[0,1],[0,1],[0,1],[0,1],[0,1],[1,0],[1,0],[0,1],[0,1],[0,1],[0,1],[0,1],[0,1],[-1,0],[0,1],[1,0],[1,0],[1,0],[0,-1],[1,0],[1,0],[1,-1],[1,0],[0,-1],[1,0],[0,-1],[0,-1],[1,1],[1,1],[1,-1],[0,-1],[0,-1],[-1,0],[0,-1],[0,-1],[1,-1],[0,-1],[1,0],[1,0],[0,1],[0,1],[0,1],[0,1],[0,1],[1,0],[0,-1],[1,-1],[1,-2],[0,-1],[1,-1],[1,1],[0,2],[0,1],[0,1],[1,1],[1,1],[1,0],[0,1],[-1,1],[0,1],[0,2],[0,1],[1,2],[0,1],[0,1],[0,1],[0,1],[1,0],[0,1],[2,0],[53,0],[71,-1],[0,1],[1,0],[1,-1],[1,1],[1,0],[0,1],[0,1],[1,0],[0,1],[0,1],[0,1],[0,1],[0,1],[0,-1],[0,-1],[1,0],[0,-1],[0,1],[0,1],[1,0],[0,1],[0,1],[0,1],[-1,1],[1,0],[0,1],[0,1],[1,0],[0,-1],[0,-1],[1,0],[0,-1],[0,-1]],[[9490,6786],[0,0]],[[9490,6786],[0,0]],[[9491,6757],[0,-1],[0,-1],[0,-1],[0,-1],[0,-1],[-1,-1],[0,-2],[0,-1],[0,-1],[-1,-1],[0,-1],[-1,-1],[0,-1],[-1,-1],[-2,0],[-1,-1],[-1,0],[-1,0],[-1,0],[-1,0],[-1,0],[0,-1],[-1,0],[0,-1],[0,-1],[-1,0],[0,-1],[0,-1],[-1,-2],[-2,-2],[-1,2],[0,3],[-1,0],[-1,0],[0,1],[-1,0],[-1,0],[0,-1],[0,-1],[-1,0],[0,-1],[-1,2],[0,1],[-1,-1],[-1,0],[-1,0],[0,1],[-1,2],[0,1],[1,0],[0,1],[-1,0],[0,1],[1,0],[0,1],[-1,0],[0,1],[1,0],[0,1],[0,1],[0,1],[1,0],[0,1],[0,1],[0,1],[0,1],[1,1],[0,1],[0,1],[0,1],[0,1],[0,1],[0,1],[0,1],[1,0],[0,1],[0,1],[0,1],[0,1],[0,1],[0,1],[0,1],[0,1],[0,1],[0,1],[1,0],[0,1],[-1,0],[0,1],[1,0],[0,1],[0,1],[0,-1],[1,0],[0,1],[0,1],[0,1],[0,1],[0,-1],[-1,0],[0,1],[0,1],[1,0],[-1,0],[0,1],[-1,0],[0,1],[0,1],[-1,1],[0,1],[0,1],[0,1],[0,1],[0,1],[0,1],[1,0],[-1,0],[0,1],[0,1],[1,0],[0,1],[0,1],[0,1],[-1,0],[0,1],[0,-1],[0,1],[-1,0],[0,-1],[0,-1],[0,1],[0,1],[-1,0],[-1,0],[0,-1],[0,1],[-1,1],[0,1],[-1,0],[0,1],[0,1],[-1,0],[0,1],[0,1],[1,0],[0,1],[1,2],[1,0],[0,1],[1,0],[0,1],[0,1],[1,0],[0,1],[0,1],[1,0],[0,1],[1,1],[0,1],[1,0],[0,1],[1,0],[0,1],[0,1],[1,0],[0,1],[1,0],[0,1],[1,1],[0,1],[1,0],[0,1],[1,1],[0,1],[1,0],[0,1],[0,1],[0,1],[-1,0],[0,1],[0,1],[0,1],[-1,0],[0,1],[0,1],[-1,0],[0,1],[-1,1],[0,1],[-1,0],[0,1],[0,1],[-1,0],[0,1],[0,1],[-1,0],[0,1],[0,1],[-1,1],[0,1],[0,1],[0,1],[-1,0],[0,1],[0,1],[-1,0],[0,1],[-1,1],[0,1],[0,1],[-1,2],[1,2],[1,3],[3,7],[2,8],[2,4],[0,-1],[1,0],[0,-1],[0,-1],[1,-1],[0,-1],[0,1],[0,-1],[1,0],[0,-1],[1,-1],[0,-1],[1,-1],[0,-1],[1,0],[0,-2],[1,0],[0,-1],[0,1],[0,1],[1,0],[0,1],[0,1],[0,1],[1,0],[0,1],[0,1],[0,1],[1,0],[0,-1],[0,-1],[3,-4],[5,-9],[0,-1],[1,-1],[0,-1],[1,0],[0,-1],[0,-1],[1,-1],[1,-1],[0,-1],[1,-1],[0,-1],[0,1],[0,1],[1,0],[0,1],[0,1],[1,0],[0,1],[0,1],[1,0],[0,1],[0,1],[1,0],[0,1],[0,1],[0,1],[1,0],[0,1],[-1,0],[0,1],[-1,1],[0,1],[0,1],[0,1],[1,1],[0,1],[0,1],[1,1],[0,1],[0,1],[1,1],[0,1],[1,0],[0,1],[0,1],[0,1],[1,2],[0,1],[1,1],[0,1],[0,1],[0,1],[1,0],[0,1],[0,1],[0,1],[1,0],[0,1],[0,1],[1,1],[0,1],[1,1],[0,1],[1,1],[0,2],[1,0],[1,2],[0,1],[1,2],[0,1],[1,0],[0,1],[0,1],[1,1],[0,1],[0,1],[1,-1],[1,-1],[0,-1],[1,-2],[1,-1],[1,3],[0,-1],[0,-1],[0,-1],[0,-1],[1,0],[0,-1],[0,-1],[0,1],[1,-1],[0,-1],[0,-1],[1,0],[1,0],[0,-1],[0,-1],[1,0],[0,1],[1,0],[0,-1],[0,-1],[0,-1],[0,-1],[0,-1],[0,-1],[-1,0],[0,-1],[1,0],[0,-1],[0,-1],[0,-1],[0,-1],[0,-1],[0,-1],[1,0],[0,-1],[0,-1],[0,-1],[0,-1],[0,-1],[0,-1],[0,-1],[0,-1],[0,-1],[0,-1],[-1,-1],[0,-1],[0,-1],[-1,0],[-1,0],[0,-1],[0,-1],[0,-1],[0,-1],[-1,0],[0,-1],[0,-1],[0,-1],[-1,0],[0,-1],[0,-1],[0,-1],[0,-1],[0,-1],[-1,-1],[1,-1],[0,-1],[1,0],[1,-2],[-1,-3],[0,-1],[-1,0],[0,-1],[-1,-2],[0,-1],[-1,-1],[0,-2],[-1,0],[0,-1],[-1,-1],[0,-1],[0,-1],[-2,-2],[0,-1],[0,-1],[-1,0],[-1,-1],[-1,0],[0,-1],[-1,0],[0,-1],[-1,0],[0,-1],[-1,-1],[-1,-1],[-1,-2],[0,-1],[-1,-1],[0,-3],[0,-1],[-1,-2],[0,-1],[0,-1],[0,-2],[-1,-1],[0,-1],[0,-1],[-1,-1],[0,-1],[-1,-1],[-1,-1],[-1,-1],[-1,0],[0,-1],[-1,0],[-1,-1],[-1,-1],[-1,0],[0,-1],[-1,0],[0,-1],[-1,-1],[-1,-2]],[[36,5954],[-3,-10],[-4,-11],[-1,-2],[0,-2],[0,-2],[1,-2],[-1,-1],[0,-1],[0,-1],[-1,-1],[-1,0],[0,1],[-1,1],[-2,1],[-1,-11],[3,-3],[1,-4],[1,-2],[0,-4],[2,-9],[1,-5],[7,0],[0,-14],[-2,0],[-1,0],[0,-1],[0,1],[0,1],[0,1],[0,1],[0,1],[0,1],[-12,-1],[-1,10],[3,0],[-1,10],[0,10],[-5,4],[0,-1],[-1,-7],[-1,-3],[0,-3],[0,3],[-1,4],[-1,9],[0,1],[2,4],[0,4],[1,1],[0,3],[-1,6],[1,2],[2,2],[2,-1],[2,-3],[1,1],[-1,1],[0,3],[0,1],[0,19],[0,1],[0,2],[1,0],[3,0],[2,0],[2,1],[1,0],[1,-1],[2,-2],[1,0],[1,0],[-1,-3]],[[0,5880],[0,3],[0,10],[0,2],[0,1],[0,1],[0,1],[0,1],[0,1],[1,0],[0,1],[0,1],[0,5],[0,9],[0,1],[0,1],[0,1],[0,1],[1,1],[2,1],[-1,3],[0,1],[0,1],[1,0],[-1,1],[0,1],[0,1],[0,1],[-1,1],[1,0],[1,1],[1,0],[1,1],[1,1],[0,-1],[1,-1],[0,-1],[1,0],[0,1],[1,0],[0,1],[0,1],[1,0],[1,1],[1,0],[1,-1],[1,0],[0,-1],[1,0],[0,-1],[0,-1],[0,-1],[0,-1],[0,-1],[1,-1],[0,-1],[0,-1],[0,-1],[0,-1],[0,-1],[0,-1],[-1,-1],[0,-1],[0,-1],[0,-1],[0,-1],[-1,0],[0,-1],[0,-1],[-1,-1],[0,-1],[0,-1],[0,-1],[0,-1],[0,-1],[0,-1],[1,-1],[0,-1],[0,-2],[0,-1],[0,-1],[1,-2],[0,-1],[0,-1],[0,-1],[-1,-1],[0,-1],[-1,-3],[-1,-1],[-1,-1],[0,-1],[0,-1],[0,-1],[0,-1],[1,-1],[0,-1],[0,-1],[0,-1],[-1,0],[0,-1],[-1,0],[-2,-1],[-1,0],[0,-1],[-1,0],[0,-2],[-1,-3],[0,-1],[0,-2],[-1,1],[-1,0],[-1,0],[0,1],[-1,0],[-1,0],[0,-1],[-1,0],[0,4],[0,2],[0,2]],[[4653,237],[0,2],[0,1],[0,1],[0,2],[2,0],[1,0],[0,-1],[0,-1],[1,-1],[0,1],[0,1],[1,0],[0,3],[-1,1],[0,-1],[-2,1],[0,12],[1,-1],[2,1],[1,-5],[-1,-6],[1,-1],[0,1],[1,0],[0,-1],[1,0],[0,8],[0,4],[0,1],[1,3],[1,1],[0,1],[1,-2],[1,2],[0,1],[0,1],[2,5],[0,-2],[0,-1],[1,-2],[0,-1],[0,-1],[0,-2],[1,1],[0,-1],[1,0],[0,1],[1,0],[0,1],[0,-1],[1,0],[-1,-2],[0,-1],[1,0],[0,-1],[0,-1],[0,-1],[0,-1],[0,-1],[0,1],[0,-3],[2,0],[0,-1],[0,-1],[0,-1],[0,-1],[0,-1],[1,0],[0,-3],[0,2],[-1,0],[-1,0],[-1,-1],[0,-2],[0,-3],[-1,-9],[-1,1],[-2,0],[-2,-12],[-1,-7],[0,-1],[0,-1],[-1,-4],[6,-8],[0,1],[1,-2],[0,2],[1,0],[0,1],[1,-1],[1,-1],[0,1],[0,1],[1,-1],[1,7],[1,6],[0,1],[1,2],[0,1],[0,1],[0,1],[1,1],[0,1],[-1,1],[-1,1],[-1,1],[0,-1],[-1,0],[1,1],[-1,0],[0,1],[1,3],[1,0],[1,-2],[0,-1],[0,-1],[-1,0],[1,0],[0,-1],[0,-1],[1,2],[0,2],[1,1],[0,1],[0,1],[1,0],[1,2],[0,1],[-1,1],[1,1],[0,1],[0,-1],[0,2],[1,0],[0,1],[0,4],[-2,0],[0,-1],[0,1],[-1,0],[0,-1],[0,-2],[0,6],[1,0],[0,1],[0,-1],[0,1],[1,0],[0,2],[0,1],[0,2],[0,1],[0,2],[-1,3],[-1,0],[0,1],[0,1],[0,3],[1,0],[0,1],[0,1],[0,1],[0,1],[0,2],[1,0],[0,5],[0,1],[2,0],[2,0],[1,0],[0,1],[0,-1],[0,-1],[-1,0],[0,-1],[0,-1],[1,-1],[0,-1],[0,-1],[0,-1],[0,-1],[-1,0],[0,-1],[0,-1],[0,-1],[0,-1],[0,-1],[0,-1],[0,-1],[0,-1],[0,-1],[0,-1],[0,1],[1,1],[0,1],[0,1],[0,1],[0,1],[0,1],[1,-1],[0,1],[1,0],[0,-1],[1,0],[0,1],[1,1],[0,1],[0,1],[-1,0],[0,1],[0,1],[0,1],[-1,0],[0,1],[0,1],[0,1],[0,1],[-1,0],[0,1],[0,1],[0,1],[0,1],[1,2],[1,1],[0,1],[1,0],[0,1],[-1,0],[-1,0],[0,1],[0,-1],[-1,0],[0,2],[0,1],[0,1],[0,-1],[0,-1],[0,1],[-1,-1],[0,-2],[1,0],[0,-1],[0,-1],[0,1],[0,-1],[0,1],[-1,-1],[0,-1],[-1,0],[0,1],[0,1],[0,1],[0,1],[1,1],[0,1],[0,1],[0,1],[1,1],[1,2],[0,4],[0,2],[0,1],[0,1],[0,1],[0,1],[0,1],[0,1],[0,1],[-1,-1],[0,1],[-1,0],[0,1],[0,2],[0,1],[0,2],[1,0],[1,0],[0,-1],[0,-1],[0,-2],[1,0],[0,1],[0,1],[1,1],[0,1],[-1,0],[0,1],[0,4],[0,9],[0,1],[0,4],[0,2],[1,1],[0,1],[0,1],[0,1],[0,1],[0,1],[0,1],[0,2],[0,4],[1,0],[0,-4],[0,-2],[0,-1],[0,-1],[0,-1],[0,-1],[-1,-1],[0,-1],[0,-2],[0,-1],[0,-1],[-1,-4],[0,-12],[4,0],[0,-5],[1,0],[0,-7],[0,-6],[2,0],[0,-3],[2,0],[0,-4],[0,-5],[0,-1],[1,-1],[-1,-2],[1,0],[2,0],[0,-1],[0,-1],[1,2],[1,1],[0,1],[2,0],[0,-1],[3,0],[2,0],[1,0],[1,0],[0,2],[0,2],[0,2],[0,1],[0,1],[0,1],[0,1],[0,1],[0,1],[0,1],[0,1],[0,1],[0,1],[-1,0],[0,1],[0,1],[1,0],[2,2],[0,2],[1,0],[-1,5],[3,5],[0,-1],[0,-3],[0,-2],[0,-1],[0,-2],[0,-1],[1,0],[1,0],[0,-1],[1,-1],[1,-1],[1,-1],[0,-1],[0,1],[1,-1],[0,-1],[1,-1],[1,4],[0,-1],[0,-1],[1,2],[0,1],[0,1],[1,0],[0,1],[1,0],[1,0],[0,-1],[0,-1],[0,-1],[0,-1],[1,0],[-1,0],[1,-1],[1,-1],[0,-1],[0,-1],[0,-1],[0,-1],[0,-3],[0,-1],[4,1],[0,-2],[0,-2],[0,-2],[1,-3],[4,7],[1,-1],[-1,0],[0,-1],[0,-1],[0,-2],[0,-1],[1,2],[1,-2],[0,1],[0,1],[2,5],[-2,3],[1,-1],[3,6],[1,-3],[0,-1],[0,-1],[0,-1],[0,-1],[0,-1],[0,-1],[1,-1],[-3,-3],[0,1],[0,-4],[1,-4],[0,-1],[0,-1],[-1,-1],[-1,-1],[2,-5],[0,2],[1,-1],[0,1],[1,-3],[0,1],[2,1],[1,0],[0,-1],[0,-1],[0,-1],[1,0],[0,-1],[1,0],[1,0],[-1,0],[1,0],[-1,0],[-1,-2],[-1,-2],[0,-1],[-1,0],[0,-1],[-1,-2],[-1,-2],[1,-3],[-1,-1],[0,-1],[-1,0],[0,-1],[0,-1],[0,-1],[0,-1],[-1,0],[0,-1],[-1,0],[1,-3],[0,-1],[0,-1],[0,-1],[1,-4],[-1,-1],[-1,0],[0,-1],[0,-1],[0,-1],[0,-1],[0,-1],[0,-1],[0,1],[0,-1],[0,-1],[-1,-2],[1,0],[-1,0],[0,-1],[0,-1],[0,-1],[-1,-2],[-1,0],[0,-1],[0,-1],[-1,-1],[-1,0],[0,-2],[-1,0],[0,1],[-1,0],[0,-1],[0,-1],[-1,0],[0,-1],[0,-1],[0,-1],[0,-1],[0,-1],[0,-1],[0,-1],[0,-1],[0,-1],[-1,-2],[0,-1],[0,-2],[0,-1],[1,0],[1,0],[1,0],[0,1],[-1,0],[0,-1],[-1,0],[0,1],[0,3],[0,1],[1,0],[0,1],[0,1],[0,1],[1,0],[1,0],[1,0],[1,0],[0,1],[1,0],[0,-1],[-1,-1],[1,-3],[0,-1],[3,-2],[1,0],[1,1],[0,1],[1,3],[0,1],[0,1],[1,1],[2,2],[0,-3],[-1,-2],[2,-1],[0,3],[1,-1],[0,-1],[0,-1],[0,-1],[0,-1],[-1,0],[-1,0],[-2,2],[0,1],[1,1],[0,2],[-1,-1],[-1,-1],[0,-1],[-1,-3],[0,-1],[-2,-4],[0,-1],[1,0],[0,1],[0,-1],[0,-1],[1,0],[0,-1],[-1,0],[1,-1],[0,-1],[-1,1],[0,-1],[-1,-1],[-1,-2],[0,-1],[0,-1],[-1,0],[0,-1],[0,-3],[0,-2],[0,-1],[0,-3],[-1,-2],[-1,0],[0,-3],[0,-2],[2,0],[0,-2],[1,0],[4,4],[0,7],[1,-1],[0,-5],[2,2],[0,1],[2,1],[0,1],[1,-1],[0,4],[2,-1],[0,2],[0,5],[0,1],[0,1],[0,1],[0,1],[0,1],[-1,1],[0,1],[-1,1],[0,1],[1,3],[1,-1],[0,-1],[0,-1],[2,-1],[0,1],[0,1],[0,1],[1,-1],[1,-1],[0,1],[1,-1],[0,3],[1,0],[0,-1],[-1,-3],[0,-1],[-1,-1],[-1,-4],[-1,1],[-1,0],[0,-2],[0,-5],[1,-1],[0,-1],[1,0],[3,3],[1,1],[1,1],[1,1],[1,1],[2,2],[0,1],[1,0],[0,1],[1,0],[0,1],[1,0],[0,1],[0,-2],[0,-1],[-1,0],[0,-1],[-1,0],[0,-1],[-2,-1],[-1,-1],[0,-1],[-2,-1],[0,-1],[-1,0],[-1,-1],[-3,-4],[-1,-2],[0,1],[-1,-2],[-1,1],[-3,-3],[-1,-1],[-1,-5],[0,-4],[0,-1],[-1,-1],[0,-1],[-1,-3],[0,-1],[0,-2],[-1,0],[-1,1],[0,1],[0,1],[0,6],[-3,2],[0,-1],[-1,0],[0,-4],[0,-3],[0,-7],[0,1],[-1,0],[-1,0],[0,-1],[0,-1],[0,-1],[0,-1],[-1,0],[0,-1],[0,-1],[0,-1],[0,-1],[0,-1],[0,-1],[0,-1],[-1,0],[0,-1],[0,-1],[0,-1],[-1,0],[0,-1],[1,0],[1,0],[0,-1],[1,0],[1,-2],[1,-1],[0,-4],[0,-4],[0,-10],[1,-1],[2,-2],[4,-3],[1,0],[1,0],[0,-1],[1,0],[-1,0],[-2,2],[-1,0],[-5,4],[-1,1],[-1,0],[-1,0],[0,1],[-1,0],[0,1],[-1,0],[0,-5],[0,-1],[0,-8],[0,-1],[-1,0],[-1,0],[-1,0],[0,-1],[-1,-4],[0,-1],[0,-2],[0,-1],[0,-3],[-1,0],[0,-1],[0,-1],[0,-1],[-1,0],[1,-1],[0,-1],[1,-1],[0,-1],[1,-1],[0,-1],[1,-1],[1,-1],[1,-3],[1,0],[0,-2],[1,0],[-1,0],[0,1],[-1,1],[-1,-3],[0,-1],[0,-1],[1,-1],[1,-3],[0,-1],[0,-1],[1,-2],[-2,-5],[1,0],[0,1],[0,1],[1,3],[0,-1],[0,-1],[1,0],[2,-7],[-1,-5],[0,-2],[-1,0],[0,-3],[1,0],[0,-3],[0,-1],[0,-1],[0,-1],[0,-1],[0,-1],[-1,0],[0,-1],[-1,0],[0,-1],[0,1],[-1,0],[0,-1],[-1,0],[0,-1],[0,1],[0,-1],[-1,-1],[0,1],[-1,0],[0,1],[0,2],[1,2],[-1,1],[0,1],[0,-2],[-1,0],[0,1],[0,2],[0,-1],[0,-1],[-1,-1],[0,-1],[0,-2],[0,-1],[0,-1],[-1,-1],[1,0],[0,-1],[0,-1],[0,-1],[0,-1],[0,-1],[0,-2],[0,-2],[1,1],[1,0],[-1,0],[0,-1],[1,0],[-2,-2],[-1,-3],[0,-1],[1,-1],[1,-2],[-1,-1],[0,-1],[-1,-1],[0,1],[-4,-9],[1,8],[1,9],[0,2],[-1,1],[0,1],[-1,0],[0,-1],[0,-3],[-1,0],[1,4],[-1,0],[0,-2],[0,1],[-1,-3],[-1,1],[1,3],[0,-1],[0,1],[0,1],[1,-1],[0,1],[1,3],[0,3],[0,1],[0,3],[0,-1],[-1,1],[0,1],[0,3],[1,-1],[0,3],[1,-1],[2,-2],[1,0],[0,1],[2,10],[-1,1],[-2,-8],[0,1],[-1,-1],[3,13],[-1,1],[1,2],[0,2],[0,-1],[0,1],[0,2],[0,-1],[-1,1],[1,2],[-2,3],[-3,-12],[0,1],[0,1],[0,1],[-1,1],[-1,1],[0,1],[0,1],[1,4],[0,1],[-1,0],[0,-1],[0,-1],[0,1],[-1,0],[1,0],[0,1],[-1,0],[0,1],[0,1],[0,1],[0,1],[0,1],[0,1],[0,1],[-1,0],[0,1],[0,1],[0,1],[0,1],[1,0],[0,1],[0,1],[0,-1],[0,1],[0,1],[-1,0],[0,-1],[0,1],[1,0],[0,1],[-1,0],[0,1],[0,1],[-1,-3],[0,-1],[0,-1],[0,1],[-1,0],[0,1],[1,0],[-1,0],[0,1],[-1,0],[1,0],[1,0],[-1,0],[1,1],[-1,0],[-1,0],[1,0],[0,1],[-1,0],[0,2],[1,0],[0,1],[0,-1],[0,1],[-1,0],[0,1],[-1,0],[0,-1],[0,1],[0,-1],[-1,-1],[0,-1],[0,-1],[0,-1],[0,-1],[-1,-1],[0,-3],[1,-3],[0,-2],[0,-2],[0,-2],[0,-1],[0,-1],[0,-5],[-1,0],[0,-16],[0,-3],[0,-1],[0,-1],[0,1],[0,1],[-1,0],[0,1],[-1,1],[0,1],[-1,0],[0,1],[-1,1],[0,1],[0,1],[0,-1],[0,-1],[-1,-1],[-1,0],[0,1],[-1,-1],[0,1],[0,-1],[-1,0],[-1,0],[0,-1],[0,-1],[0,-1],[0,-1],[0,-1],[0,-4],[0,-1],[-1,0],[-1,0],[0,-1],[0,1],[0,1],[0,1],[0,-2],[-1,-1],[-2,-1],[-1,0],[0,-5],[1,-7],[-1,1],[-1,0],[0,1],[-1,2],[0,1],[2,0],[0,2],[-2,0],[0,1],[2,-1],[0,1],[-1,0],[1,0],[0,1],[-2,0],[0,2],[0,5],[0,1],[-1,1],[-1,0],[0,1],[0,1],[0,1],[-1,0],[-1,0],[0,1],[-1,0],[0,1],[0,1],[0,1],[0,-2],[-1,0],[0,-1],[-1,0],[0,1],[0,1],[0,1],[-1,0],[0,1],[-1,0],[0,1],[0,1],[0,1],[0,2],[0,1],[-1,0],[1,0],[0,1],[-1,0],[0,-1],[0,1],[0,-1],[0,-1],[-1,0],[0,1],[0,-1],[0,-2],[-1,1],[0,1],[0,3],[0,1],[0,1],[0,-1],[0,1],[0,-1],[1,1],[0,1],[-1,0],[0,1],[0,1],[-1,-1],[0,1],[0,-1],[-1,0],[0,1],[0,-1],[0,3],[0,-1],[-1,0],[0,1],[0,1],[-1,1],[0,1],[-1,1],[0,-2],[0,3],[0,-1],[-1,0],[1,1],[0,1],[0,1],[1,0],[0,1],[1,1],[-1,1],[0,1],[-1,0],[0,4],[-1,2],[-1,5],[0,1],[-1,0],[-2,3],[0,1],[-1,1],[0,12],[1,0],[1,1],[3,-1],[0,9],[0,4],[0,3],[0,2],[-1,2],[0,3],[-1,1],[0,2],[0,3],[-1,0],[-1,-1],[-1,-1],[0,-1],[-1,0],[-1,-1],[-1,-1],[-1,0],[0,-1],[-1,0],[-1,-1],[0,-1],[-1,0],[-1,0],[-1,-1],[-1,0],[-1,-1],[0,1],[1,0],[2,1],[1,1],[0,1],[0,1],[1,0],[0,-1],[1,0],[0,1],[1,0],[1,1],[2,2],[1,1],[1,0],[0,1],[0,1],[0,1],[0,1],[0,1],[-1,0],[0,-1],[-1,0],[0,1],[0,1],[0,1],[0,1],[0,1],[0,1],[0,1],[0,1],[-1,0],[0,2],[0,1],[0,1],[0,1],[-3,0],[0,2],[0,1],[0,3],[-2,0],[-1,0],[-1,0],[0,2],[0,1],[-1,0],[0,1],[1,0],[0,3],[0,1],[0,1],[0,1],[0,1],[0,1],[0,1],[0,11],[0,2],[-2,-2],[0,1],[-1,0],[0,1],[1,0],[-1,1],[0,1],[1,0],[0,1],[-1,1],[1,1],[1,0],[0,4],[0,1],[1,-1],[0,1],[0,1],[0,2],[1,3],[0,1],[-1,1],[0,1],[-1,0],[0,-1],[0,-1],[-1,0],[0,1],[0,1],[0,1],[0,1],[-1,1],[-1,1],[-1,1],[-3,4],[-1,1],[-1,1],[0,1],[1,-1],[1,4],[0,1],[0,2],[0,3],[1,2],[-1,1],[-1,4],[-1,1],[-1,-3],[0,-3],[-1,2],[-1,-4],[1,4],[-2,2],[0,1],[0,-1],[-1,0],[0,1],[-1,-1],[0,-2],[-1,-4],[0,-1],[1,-3],[0,-1],[0,-1],[-1,-2],[0,1],[1,3],[-1,3],[0,1],[-1,3],[-1,0],[0,-1],[0,-1],[0,-1],[-1,1],[0,3],[0,1],[0,1],[0,1],[1,1],[0,1],[0,1],[1,1],[1,1],[0,1],[0,1],[0,1],[1,5],[-1,1],[0,-3],[-1,1],[0,-1],[-1,0],[-1,0],[0,1]],[[4720,191],[0,-1],[0,-1],[1,0],[0,-1],[0,-1],[0,-2],[1,0],[0,-1],[0,-1],[0,-1],[0,-1],[0,-1],[1,0],[0,-1],[0,-1],[1,0],[1,0],[2,0],[1,0],[0,1],[1,0],[0,1],[1,2],[0,1],[0,1],[0,1],[1,1],[0,2],[-4,0],[-1,0],[-1,0],[0,3],[0,1],[0,2],[0,1],[-2,0],[0,-3],[-2,0],[-1,0],[0,-1]],[[4690,196],[0,-1],[0,-1],[0,-2],[0,-1],[0,-1],[0,1],[1,0],[0,-1],[0,-1],[0,-1],[-1,0],[0,-1],[0,-1],[1,0],[1,1],[0,1],[0,-1],[0,-1],[1,2],[1,-1],[0,-1],[1,0],[0,1],[0,-1],[1,0],[0,1],[0,-1],[1,0],[-1,-1],[1,-2],[0,1],[1,0],[1,1],[-1,2],[-1,0],[0,1],[0,-1],[-1,0],[0,1],[0,1],[1,0],[0,1],[0,1],[-1,1],[-1,1],[1,2],[0,-1],[0,1],[1,3],[-1,1],[-1,1],[-1,2],[0,1],[0,1],[0,1],[0,1],[-1,0],[0,1],[-1,1],[0,-1],[0,-2],[-1,-3],[-1,0],[0,-1],[0,-1],[0,-1],[1,-1],[-1,-1],[0,-1]],[[4718,178],[1,0],[1,0],[1,0],[0,1],[0,1],[0,1],[0,-1],[-1,0],[0,-1],[0,1],[-1,0],[1,0],[0,1],[0,1],[0,1],[0,1],[0,1],[0,1],[0,1],[-1,0],[0,1],[-1,-2],[0,-1],[0,-7]],[[4737,167],[1,0],[0,1],[1,0],[0,-1],[1,0],[0,-1],[1,1],[2,0],[-1,0],[0,2],[0,1],[0,1],[0,1],[0,4],[0,1],[0,1],[0,1],[0,1],[0,1],[0,1],[0,-1],[0,1],[-1,0],[1,0],[0,1],[0,1],[-1,-2],[-1,-1],[-3,-6],[1,0],[0,-1],[-1,0],[1,0],[-1,-1],[0,-1],[0,-2],[0,-1],[0,-2]],[[4693,54],[1,0],[0,-1],[0,-1],[0,-1],[1,0],[0,1],[0,1],[1,0],[0,-1],[0,-1],[0,1],[0,1],[0,1],[0,1],[0,1],[0,1],[0,1],[-1,0],[0,-2],[0,-1],[0,-1],[-1,0],[1,3],[0,5],[0,-2],[-1,-2],[0,-3],[-1,-1]],[[4716,259],[0,-1],[0,-3],[0,-1],[1,0],[0,-1],[0,-1],[-1,0],[0,-1],[0,-1],[0,-1],[1,-1],[0,-1],[1,-2],[2,-6],[0,1],[0,-1],[0,1],[1,2],[0,3],[0,1],[0,2],[0,1],[1,2],[0,1],[0,5],[1,4],[-1,1],[0,2],[0,2],[-1,0],[-1,0],[0,-1],[0,-1],[0,1],[-1,-1],[0,1],[0,1],[-1,0],[0,-1],[-1,0],[1,-1],[0,-1],[0,-1],[-1,0],[0,-1],[-1,-1],[0,-1]],[[4701,256],[0,-1],[0,-1],[2,-8],[1,0],[0,-1],[0,-1],[0,-1],[0,-1],[0,-1],[1,-2],[0,-1],[0,1],[1,2],[0,1],[0,1],[1,2],[0,1],[1,3],[1,1],[0,1],[-1,0],[0,1],[0,-1],[-1,0],[0,1],[0,1],[0,1],[0,1],[1,1],[0,2],[0,1],[0,1],[0,1],[0,1],[-1,0],[-1,-1],[-1,0],[-1,0],[0,-1],[-1,0],[0,-1],[-1,-1],[0,-2],[-1,0]],[[4696,70],[2,-1],[0,-2],[-1,0],[2,-1],[-2,1],[0,-1],[2,-1],[0,-4],[0,-5],[0,1],[0,-1],[1,0],[0,4],[2,0],[0,-1],[1,0],[0,1],[0,2],[0,-2],[0,1],[1,1],[0,1],[0,1],[-1,-2],[0,1],[0,1],[-1,0],[0,1],[3,-1],[0,1],[0,3],[0,2],[-2,1],[0,1],[0,1],[0,1],[0,1],[-1,1],[0,7],[-3,-3],[-1,0],[-2,-7],[0,-1],[0,-2]],[[4689,65],[0,-1],[1,3],[1,-2],[2,3],[-2,-6],[-1,2],[0,-2],[0,-1],[0,-1],[0,1],[1,0],[1,0],[2,10],[0,-1],[-1,0],[0,1],[-1,-3],[0,1],[1,1],[1,3],[-2,-4],[0,2],[1,1],[0,1],[-1,-1],[0,-1],[0,-1],[-1,-2],[0,1],[-1,-1],[-1,-1],[0,-2]],[[4683,256],[1,0],[0,-1],[0,-1],[1,1],[0,1],[0,1],[0,1],[1,0],[0,1],[0,1],[0,1],[0,1],[0,1],[0,1],[0,1],[-1,0],[0,-1],[0,-1],[-1,-1],[1,0],[0,-1],[0,-1],[-1,-2],[0,-1],[-1,0],[0,-1]],[[4686,271],[0,-1],[0,-1],[0,-1],[0,-1],[0,-1],[1,0],[0,1],[0,1],[0,1],[0,1],[-1,0],[0,1]],[[4684,265],[1,0],[0,1],[0,1],[0,1],[0,1],[0,1],[0,1],[1,0],[0,1],[-1,0],[0,1],[0,-1],[0,-1],[-1,-1],[1,1],[-1,-1],[0,-1],[0,-1],[0,-3]],[[4685,271],[1,-1],[0,-2],[-1,0],[0,-2],[1,0],[0,1],[0,1],[0,1],[0,1],[0,1],[-1,0]],[[4738,72],[0,-1],[0,-1],[0,-3],[1,-2],[1,4],[0,1],[0,1],[0,1],[-1,1],[0,-1],[0,1],[0,-1],[-1,0]],[[4709,218],[0,-1],[1,-1],[0,-2],[0,-1],[1,0],[0,-1],[0,-1],[0,-2],[0,-1],[0,-1],[3,-5],[0,-1],[1,-1],[0,11],[0,1],[1,0],[-4,9],[0,1],[-1,1],[0,1],[-2,-6]],[[4705,188],[0,-1],[2,0],[0,1],[0,4],[0,3],[0,1],[1,0],[0,2],[-1,1],[0,-2],[-1,-1],[0,-3],[-1,-1],[0,-1],[0,-3]],[[4734,28],[2,0],[0,-1],[0,1],[0,1],[0,2],[0,1],[0,-1],[0,-1],[-1,0],[0,-1],[-1,0],[0,-1]],[[4731,68],[1,-2],[1,3],[0,1],[-1,0],[0,-1],[-1,0],[1,-1],[-1,0]],[[4695,63],[0,-1],[1,0],[0,1],[1,0],[0,3],[0,1],[-1,0],[0,-1],[0,1],[0,1],[-1,0],[0,-1],[1,0],[0,-2],[-1,0],[0,-1],[1,0],[0,-1],[-1,0]],[[4735,74],[0,-1],[1,-1],[-1,-3],[1,0],[0,-1],[0,-1],[1,0],[0,2],[1,0],[0,1],[0,1],[-1,1],[0,1],[0,-1],[-2,3],[0,-1]],[[4694,74],[0,-1],[0,-1],[0,-1],[1,-1],[0,1],[0,1],[0,2],[1,-2],[0,1],[2,7],[-1,0],[-2,1],[-1,-1],[0,-6]],[[4700,258],[0,-1],[1,1],[1,2],[-1,0],[0,-1],[-1,0],[0,1],[0,-1],[0,-1]],[[4738,58],[0,-1],[1,1],[0,1],[0,1],[-1,0],[0,-2]],[[4671,259],[0,-1],[0,-1],[0,-1],[1,1],[-1,3],[0,-1]],[[4689,91],[1,-3],[1,0],[1,0],[-1,1],[0,1],[0,-1],[0,1],[-1,3],[1,1],[-1,0],[-1,-3]],[[4668,254],[1,-2],[1,2],[0,1],[-1,1],[0,-1],[-1,-1]],[[4733,70],[1,-1],[0,-1],[0,-1],[0,2],[0,1],[0,-1],[0,1],[-1,0]],[[4694,59],[0,-1],[1,6],[0,1],[0,-1],[0,-1],[0,-1],[0,-1],[-1,-2]],[[4733,8],[3,6],[0,1],[-1,-3],[-1,1],[1,1],[-1,0],[0,-3],[-1,-2],[0,-1]],[[4735,68],[1,-1],[0,-1],[1,0],[-1,1],[-1,2],[0,-1]],[[4693,62],[1,3],[1,4],[0,1],[-2,-8]],[[4692,81],[1,-3],[0,1],[0,4],[-1,-1],[0,-1]],[[4739,60],[1,4],[-1,-2],[0,-2]],[[4737,44],[1,-1],[0,2],[0,1],[-1,-2]],[[4737,42],[1,-2],[0,1],[0,1],[-1,1],[0,-1]],[[4697,48],[1,0],[0,8],[-1,1],[0,-9]],[[4734,78],[1,-2],[1,2],[0,1],[0,1],[-2,-2]],[[4731,77],[1,0],[0,1],[-1,0],[0,-1]],[[4729,78],[1,-2],[0,1],[1,0],[0,1],[-2,0]],[[4726,81],[1,0],[0,1],[-1,0],[0,-1]],[[4690,94],[1,0],[0,1],[-1,-1]],[[4687,87],[1,-1],[0,2],[-1,-1]],[[8264,1939],[4,9],[0,17],[-2,5],[-1,11],[2,4],[-3,12],[-3,-2],[-3,9],[-2,9],[1,8],[-7,26],[4,19],[-3,4],[-7,23],[1,5],[-2,6],[-2,-3],[-5,10],[0,11],[-3,8],[-7,-2],[-6,7],[0,4],[-4,11],[-2,-2],[-6,21],[2,5],[-1,3],[3,7],[-1,5],[-1,5],[0,10],[0,8],[-4,6],[3,10],[-1,4],[2,13],[-3,14],[0,43],[-7,9],[0,14],[-5,6],[2,1],[0,11],[-2,-2],[-1,13],[-3,10],[-3,14],[2,1],[2,23],[-1,4],[1,0],[-1,4],[-2,5],[0,4],[-8,17],[-14,29],[-5,-1],[-2,2],[-9,10],[-10,16],[-4,15],[-1,7],[2,15],[77,182],[7,-6],[8,0],[5,-13],[6,-11],[5,0],[2,-28],[-1,-64],[-1,-1],[-2,2],[-4,0],[-1,2],[-1,3],[-2,-1],[-2,0],[-5,-5],[-1,3],[-1,-12],[-3,-2],[0,-3],[-3,1],[-1,-7],[-2,-7],[1,-11],[0,-16],[9,-9],[7,-16],[10,-6],[1,6],[1,22],[0,2],[0,5],[1,4],[-1,4],[2,106],[-2,27],[2,-1],[1,-3],[2,-9],[1,-6],[6,-2],[5,-10],[4,-6],[8,-5],[1,-5],[5,-11],[3,0],[1,-5],[1,-2],[4,-3],[3,-3],[2,-6],[2,0],[1,-6],[7,-10],[0,-3],[7,-12],[1,-8],[1,1],[8,-12],[-1,-10],[2,-2],[-1,-3],[2,-7],[2,0],[0,-5],[1,1],[1,-5],[2,-7],[2,-1],[7,-4],[3,1],[1,-4],[2,3],[8,-19],[0,-7],[1,-1],[3,-8],[0,-3],[3,-11],[2,0],[-1,-3],[-3,-18],[0,-9],[0,-14],[0,-12],[-3,-38],[-1,-7],[2,-6],[3,-8],[2,8],[3,-8],[-1,-7],[0,-6],[-2,-4],[-1,5],[-1,-2],[-1,5],[-1,1],[0,-3],[-2,0],[0,2],[0,1],[-1,0],[0,-1],[0,1],[-1,1],[0,1],[-1,3],[-1,2],[-2,-9],[-1,-9],[-6,-32],[-4,-9],[-2,-13],[-11,-24],[-10,-37],[-2,-30],[1,-12],[-4,-16],[-4,-8],[-3,-8],[-7,-46],[0,-17],[-2,-8],[-5,-24],[-5,-32],[-6,-36],[0,-10],[-2,-15],[-6,-15],[-5,0],[-5,-11],[3,15]],[[6401,6006],[1,2],[2,2],[1,2],[1,2],[1,0],[1,1],[0,2],[1,0],[0,1],[0,1],[0,2],[0,1],[0,4],[-1,0],[1,3],[1,0],[0,1],[0,3],[1,1],[1,-1],[2,6],[-2,-1],[-2,1],[-3,2],[-2,0],[-1,3],[-1,0],[0,1],[2,0],[1,11],[1,0],[1,0],[1,0],[1,0],[-1,-3],[4,-1],[-1,-5],[-1,-4],[0,-1],[0,-3],[1,0],[3,0],[1,2],[-1,2],[2,-1],[0,-3],[-1,-3],[0,-3],[0,-2],[-1,-3],[-1,-2],[-2,-5],[-2,-4],[-1,-2],[0,-1],[0,-4],[0,-3],[0,-3],[0,-2],[1,-5],[1,-4],[2,-6],[1,-5],[1,-2],[0,-7],[0,-3],[1,-7],[0,-6],[0,-3],[-1,1],[-2,1],[0,-2],[-2,1],[-4,3],[-1,0],[-1,2],[-4,5],[-4,1],[-4,2],[-3,1],[0,3],[0,10],[0,1],[0,3],[1,1],[-2,2],[-1,3],[1,4],[1,-1],[0,1],[0,1],[0,2],[0,-1],[0,3],[-1,-1],[0,1],[0,1],[0,1],[1,2],[-1,2],[-1,1],[0,1],[3,0],[0,-2],[0,-1],[0,1],[0,1],[0,-2],[0,-1],[0,-1],[0,-3],[0,-1],[2,-1],[0,-2],[2,6],[1,5],[0,1],[-3,0],[0,-1],[-1,-1],[-1,2],[1,3],[-1,0],[-1,0],[-1,-1],[1,-2],[-2,0],[0,-1],[0,-1],[0,-1],[0,-3],[0,-1],[-1,-2],[0,-1],[0,-4],[-3,4],[0,2],[1,1],[0,2],[0,7],[0,4],[-2,2],[-1,0],[-1,0],[0,1],[-2,2],[-1,1],[-1,0],[-1,2],[-1,0],[-3,4],[-5,9],[4,5],[5,-9],[0,1],[3,11],[1,1],[3,-1],[0,-2],[1,-5],[1,0],[1,0],[1,0],[0,-1],[1,-1],[0,-11],[0,-3],[1,0],[0,-3],[2,2],[-1,4],[0,1],[0,1],[0,1],[1,0],[1,0],[1,0],[3,0],[0,6],[0,2],[0,3],[-3,0],[0,3],[3,0],[6,0],[0,-5],[2,0],[0,-8],[0,-6],[-1,0],[-1,-1],[0,1],[0,-2],[-2,-2],[-1,-3],[-1,0],[-1,-3],[0,-1],[1,-1],[1,-1],[0,1],[1,-1],[0,-1],[1,-1],[0,-1]],[[6401,6006],[0,1],[1,1],[0,1],[1,0],[0,1],[1,1],[1,0],[0,1],[0,1],[1,0],[0,1],[1,0],[0,1],[1,0],[0,1],[0,1],[1,0],[0,1],[1,1],[0,1],[0,1],[1,0],[0,1],[0,1],[1,1],[0,1],[0,1],[1,0],[0,1],[0,1],[0,1],[1,1],[0,1],[0,1],[0,1],[1,0],[0,1],[0,1],[0,1],[0,1],[0,1],[0,1],[0,1],[1,1],[0,1],[0,1],[1,-1],[1,0],[1,0],[0,-1],[-1,-2],[0,-3],[-1,-2],[0,-1],[0,-1],[0,-2],[-1,-3],[-1,-1],[-1,-2],[0,-1],[-1,-1],[-1,-2],[-1,-1],[0,-2],[-1,-3],[0,-1],[0,-2],[0,-4],[0,-3],[0,-3],[0,-4],[1,-2],[1,-3],[1,-1],[0,-3],[1,-3],[1,-5],[1,-4],[0,-4],[0,-1],[0,-4],[0,-4],[1,-1],[0,-2],[0,-2],[0,-1],[0,-1],[0,-2],[0,-4],[-1,-4],[0,-2],[-1,-3],[0,-3],[-1,-3],[-1,-5],[-1,-4],[-1,-1],[-2,-4],[-1,-3],[-1,-2],[-1,-1],[-2,-9],[0,-1],[-1,-2],[-1,-6],[-2,-7],[0,1],[-1,0],[0,1],[-1,0],[0,1],[0,1],[0,1],[0,1],[0,1],[0,1],[0,1],[-1,1],[0,1],[0,1],[-1,0],[0,1],[-1,1],[0,1],[-1,0],[0,1],[0,1],[-1,0],[0,1],[0,1],[-1,0],[0,1],[0,2],[-1,1],[0,1],[0,1],[-1,0],[0,1],[0,1],[0,1],[-1,2],[0,1],[0,1],[0,1],[-1,1],[0,1],[0,1],[0,1],[0,1],[0,1],[0,2],[0,1],[0,1],[0,1],[0,1],[0,1],[1,1],[0,1],[0,1],[0,1],[0,1],[0,1],[0,1],[1,1],[0,1],[0,1],[0,1],[0,1],[0,1],[0,1],[0,1],[0,1],[0,1],[0,1],[1,0],[0,1],[0,2],[0,2],[0,1],[0,1],[0,1],[0,2],[0,2],[0,1],[0,1],[1,1],[0,1],[0,1],[0,1],[1,0],[0,1],[0,1],[0,1],[0,1],[1,0],[0,1],[0,1],[0,1],[0,1],[1,0],[0,1],[0,1],[0,1],[1,1],[0,1],[0,1],[0,1],[0,1],[1,0],[0,1],[0,1],[0,1],[0,1],[1,0],[0,1],[0,1],[0,1],[0,1],[1,0],[0,1],[0,1],[0,1],[1,1],[0,1],[0,1],[0,1],[1,1],[0,1],[0,1]],[[3807,9137],[240,-5],[110,80],[2,-503],[-365,-15],[0,393],[13,50]],[[7693,4665],[-12,1],[-4,0],[-3,0],[-17,1],[-3,0],[-1,0],[-5,0],[-8,0],[-2,0],[-5,1],[-1,0],[0,5],[-2,4],[0,4],[-6,11],[-4,11],[-3,15],[-2,11],[-2,18],[0,26],[-1,-1],[-1,1],[-1,6],[0,3],[0,1],[-2,1],[-1,2],[0,11],[1,5],[0,1],[-1,1],[-1,2],[3,8],[3,2],[1,2],[1,3],[-2,1],[-1,1],[-2,-2],[-1,3],[1,3],[1,0],[1,1],[1,4],[0,1],[2,1],[0,2],[-1,3],[-1,4],[1,2],[1,3],[1,3],[-1,2],[-1,4],[0,1],[1,4],[0,3],[3,4],[-1,6],[-1,3],[0,2],[0,2],[3,4],[0,3],[0,2],[1,2],[1,3],[1,1],[1,4],[2,-1],[1,4],[1,3],[0,-3],[0,-4],[1,-1],[1,-3],[1,0],[0,-1],[1,-4],[1,-4],[2,4],[0,6],[0,3],[1,-2],[1,-4],[1,-2],[1,2],[1,-4],[1,2],[1,0],[1,-2],[0,-3],[1,-1],[1,1],[2,1],[1,0],[0,3],[-1,3],[1,3],[2,0],[0,7],[1,0],[1,-1],[0,-1],[-1,-1],[0,-4],[1,0],[1,2],[0,6],[2,1],[1,0],[-1,-3],[1,-1],[0,3],[1,0],[0,-1],[0,-1],[1,-1],[0,-2],[0,-1],[2,2],[1,-1],[1,-3]]],"transform":{"scale":[0.004895070407040704,0.0015866579457945796],"translate":[-121.5883449,29.1862572]}}